<?xml version='1.0' encoding='utf-8'?>
<!DOCTYPE list SYSTEM "variation.dtd">
<!--AUTHOR: nexvill-->
<list>
	<augmentation type="accessory_angel_earring">
		<stone id="81729">
			<variation id="1">
				<category probability="100">
					<option id="35197" chance="2.5"/>
					<option id="35198" chance="2.5"/>
					<option id="35199" chance="2.5"/>
					<option id="35200" chance="2.5"/>
					<option id="35201" chance="2.5"/>
					<option id="35202" chance="2.5"/>
					<option id="35203" chance="2.5"/>
					<option id="35204" chance="2.5"/>
					<option id="35205" chance="2.5"/>
					<option id="35206" chance="2.5"/>
					<option id="35207" chance="2.5"/>
					<option id="35208" chance="2.5"/>
					<option id="35209" chance="2.5"/>
					<option id="35210" chance="2.5"/>
					<option id="35211" chance="2.5"/>
					<option id="35212" chance="2.5"/>
					<option id="35213" chance="2.5"/>
					<option id="35214" chance="2.5"/>
					<option id="35215" chance="2.5"/>
					<option id="35216" chance="2.5"/>
					<option id="35217" chance="2.5"/>
					<option id="35218" chance="2.5"/>
					<option id="35219" chance="2.5"/>
					<option id="35220" chance="2.5"/>
					<option id="35221" chance="2.5"/>
					<option id="35222" chance="2.5"/>
					<option id="35223" chance="2.5"/>
					<option id="35224" chance="2.5"/>
					<option id="35225" chance="2.5"/>
					<option id="35226" chance="2.5"/>
					<option id="35227" chance="2.5"/>
					<option id="35228" chance="2.5"/>
					<option id="35229" chance="2.5"/>
					<option id="35230" chance="2.5"/>
					<option id="35231" chance="2.5"/>
					<option id="35232" chance="2.5"/>
					<option id="35233" chance="2.5"/>
					<option id="35234" chance="2.5"/>
					<option id="35235" chance="2.5"/>
					<option id="35236" chance="2.5"/>
				</category>
			</variation>
			<variation id="2">
				<category probability="100">
					<option id="35237" chance="2.2727"/>
					<option id="35238" chance="2.2727"/>
					<option id="35239" chance="2.2727"/>
					<option id="35240" chance="2.2727"/>
					<option id="35241" chance="2.2727"/>
					<option id="35242" chance="2.2727"/>
					<option id="35243" chance="2.2727"/>
					<option id="35244" chance="2.2727"/>
					<option id="35245" chance="2.2727"/>
					<option id="35246" chance="2.2727"/>
					<option id="35247" chance="2.2727"/>
					<option id="35248" chance="2.2727"/>
					<option id="35249" chance="2.2727"/>
					<option id="35250" chance="2.2727"/>
					<option id="35251" chance="2.2727"/>
					<option id="35252" chance="2.2727"/>
					<option id="35253" chance="2.2727"/>
					<option id="35254" chance="2.2727"/>
					<option id="35255" chance="2.2727"/>
					<option id="35256" chance="2.2727"/>
					<option id="35257" chance="2.2727"/>
					<option id="35258" chance="2.2727"/>
					<option id="35259" chance="2.2727"/>
					<option id="35260" chance="2.2727"/>
					<option id="35261" chance="2.2727"/>
					<option id="35262" chance="2.2727"/>
					<option id="35263" chance="2.2727"/>
					<option id="35264" chance="2.2727"/>
					<option id="35265" chance="2.2727"/>
					<option id="35266" chance="2.2727"/>
					<option id="35267" chance="2.2727"/>
					<option id="35268" chance="2.2727"/>
					<option id="35269" chance="2.2727"/>
					<option id="35270" chance="2.2727"/>
					<option id="35271" chance="2.2727"/>
					<option id="35272" chance="2.2727"/>
					<option id="35273" chance="2.2727"/>
					<option id="35274" chance="2.2727"/>
					<option id="35275" chance="2.2727"/>
					<option id="35276" chance="2.2727"/>
					<option id="35277" chance="2.2727"/>
					<option id="35278" chance="2.2727"/>
					<option id="35279" chance="2.2727"/>
					<option id="35280" chance="2.2727"/>
				</category>
			</variation>
		</stone>
	</augmentation>
</list>