<?xml version="1.0" encoding="utf-8"?>
<!DOCTYPE list SYSTEM "spawn.dtd">
<list>
	<!-- 1 часть квеста на нублес -->
    <spawn count="1" respawn="5" respawn_random="0" period_of_day="none">
		<territory>
			<add x="20742" y="184815" zmin="-3355" zmax="-3155"/>
			<add x="21085" y="185004" zmin="-3355" zmax="-3155"/>
			<add x="21388" y="184856" zmin="-3355" zmax="-3155"/>
			<add x="20945" y="184213" zmin="-3355" zmax="-3155"/>
			<add x="20671" y="184509" zmin="-3355" zmax="-3155"/>
		</territory>
		<npc id="27113"/><!--Baraham-->
	</spawn>
	<spawn count="7" respawn="5" respawn_random="0" period_of_day="none">
		<territory>
			<add x="181224" y="20600" zmin="-3204" zmax="-2904" />
			<add x="178920" y="21656" zmin="-3204" zmax="-2904" />
			<add x="178856" y="25652" zmin="-3204" zmax="-2904" />
			<add x="182924" y="25636" zmin="-3204" zmax="-2904" />
			<add x="183792" y="24912" zmin="-3204" zmax="-2904" />
			<add x="183744" y="20632" zmin="-3204" zmax="-2904" />
		</territory>
		<npc id="20669" /><!--Taik Orc Supply Leader-->
	</spawn>
	<spawn count="7" respawn="5" respawn_random="0" period_of_day="none">
		<territory>
			<add x="181200" y="20008" zmin="-3216" zmax="-2916" />
			<add x="183752" y="20068" zmin="-3216" zmax="-2916" />
			<add x="183776" y="15716" zmin="-3216" zmax="-2916" />
			<add x="182956" y="15064" zmin="-3216" zmax="-2916" />
			<add x="178900" y="15076" zmin="-3216" zmax="-2916" />
			<add x="178880" y="18820" zmin="-3216" zmax="-2916" />
		</territory>
		<npc id="20669" /><!--Taik Orc Supply Leader-->
	</spawn>
	<spawn count="3" respawn="5" respawn_random="0" period_of_day="none">
		<territory>
			<add x="179752" y="15484" zmin="-3204" zmax="-2904" />
			<add x="179752" y="16236" zmin="-3204" zmax="-2904" />
			<add x="180756" y="16236" zmin="-3204" zmax="-2904" />
			<add x="180756" y="15484" zmin="-3204" zmax="-2904" />
		</territory>
		<npc id="20669" /><!--Taik Orc Supply Leader-->
	</spawn>
	<spawn count="2" respawn="5" respawn_random="0" period_of_day="none">
		<territory>
			<add x="181748" y="15520" zmin="-3204" zmax="-2904" />
			<add x="181748" y="16272" zmin="-3204" zmax="-2904" />
			<add x="182752" y="16272" zmin="-3204" zmax="-2904" />
			<add x="182752" y="15520" zmin="-3204" zmax="-2904" />
		</territory>
		<npc id="20669" /><!--Taik Orc Supply Leader-->
	</spawn>
	<spawn count="3" respawn="5" respawn_random="0" period_of_day="none">
		<territory>
			<add x="179772" y="17900" zmin="-3204" zmax="-2904" />
			<add x="179772" y="18652" zmin="-3204" zmax="-2904" />
			<add x="180776" y="18652" zmin="-3204" zmax="-2904" />
			<add x="180776" y="17900" zmin="-3204" zmax="-2904" />
		</territory>
		<npc id="20669" /><!--Taik Orc Supply Leader-->
	</spawn>
	<spawn count="2" respawn="5" respawn_random="0" period_of_day="none">
		<territory>
			<add x="181752" y="17924" zmin="-3204" zmax="-2904" />
			<add x="181752" y="18676" zmin="-3204" zmax="-2904" />
			<add x="182756" y="18676" zmin="-3204" zmax="-2904" />
			<add x="182756" y="17924" zmin="-3204" zmax="-2904" />
		</territory>
		<npc id="20669" /><!--Taik Orc Supply Leader-->
	</spawn>
	<spawn count="3" respawn="5" respawn_random="0" period_of_day="none">
		<territory>
			<add x="179748" y="21916" zmin="-3204" zmax="-2904" />
			<add x="179748" y="22668" zmin="-3204" zmax="-2904" />
			<add x="180752" y="22668" zmin="-3204" zmax="-2904" />
			<add x="180752" y="21916" zmin="-3204" zmax="-2904" />
		</territory>
		<npc id="20669" /><!--Taik Orc Supply Leader-->
	</spawn>
	<spawn count="3" respawn="5" respawn_random="0" period_of_day="none">
		<territory>
			<add x="181744" y="21952" zmin="-3204" zmax="-2904" />
			<add x="181744" y="22704" zmin="-3204" zmax="-2904" />
			<add x="182748" y="22704" zmin="-3204" zmax="-2904" />
			<add x="182748" y="21952" zmin="-3204" zmax="-2904" />
		</territory>
		<npc id="20669" /><!--Taik Orc Supply Leader-->
	</spawn>
	<spawn count="3" respawn="5" respawn_random="0" period_of_day="none">
		<territory>
			<add x="179768" y="24332" zmin="-3204" zmax="-2904" />
			<add x="179768" y="25084" zmin="-3204" zmax="-2904" />
			<add x="180772" y="25084" zmin="-3204" zmax="-2904" />
			<add x="180772" y="24332" zmin="-3204" zmax="-2904" />
		</territory>
		<npc id="20669" /><!--Taik Orc Supply Leader-->
	</spawn>
	<spawn count="3" respawn="5" respawn_random="0" period_of_day="none">
		<territory>
			<add x="181748" y="24356" zmin="-3204" zmax="-2904" />
			<add x="181748" y="25108" zmin="-3204" zmax="-2904" />
			<add x="182752" y="25108" zmin="-3204" zmax="-2904" />
			<add x="182752" y="24356" zmin="-3204" zmax="-2904" />
		</territory>
		<npc id="20669" /><!--Taik Orc Supply Leader-->
	</spawn>
</list>