<?xml version="1.0" encoding="UTF-8"?>
<!DOCTYPE list SYSTEM "item.dtd">
<list>
	<!-- 
		S Weapons
	-->
	<weapon id="101157" name="Dark Legion's Edge Lv.1">
		<set name="grind_commission" value="3111150"/>
		<set name="grind_point" value="10370500"/>
		<set name="variation_group_id" value="1"/>
		<set name="damage_range" value="0;0;40;120"/>
		<set name="crystal_count" value="1659"/>
		<set name="crystal_type" value="S"/>
		<set name="variation_group_id" value="1"/>
		<set name="icon" value="icon.weapon_dark_legions_edge_i00"/>
		
		<set name="type" value="SWORD"/>
		<set name="weight" value="1320"/>
		<set name="soulshots" value="2"/>
		<set name="spiritshots" value="2"/>
		<set name="rnd_dam" value="10"/>
		<equip>
			<slot id="RIGHT_HAND"/>
		</equip>
		<skills>
			<skill id="100011" level="1"/>
		</skills>
		<for>
			<add stat="pAtk" order="0x10" value="531"/>
			<add stat="mAtk" order="0x10" value="114"/>
			<set stat="basePAtkSpd" order="0x08" value="379"/>
			<set stat="basePCritRate" order="0x08" value="80"/>
		</for>
	</weapon>
	<weapon id="101158" name="Dark Legion's Edge Lv.2">
		<set name="grind_commission" value="3111150"/>
		<set name="grind_point" value="10370500"/>
		<set name="variation_group_id" value="1"/>
		<set name="damage_range" value="0;0;40;120"/>
		<set name="crystal_count" value="1659"/>
		<set name="crystal_type" value="S"/>
		<set name="variation_group_id" value="1"/>
		<set name="icon" value="icon.weapon_dark_legions_edge_i00"/>
		
		<set name="type" value="SWORD"/>
		<set name="weight" value="1320"/>
		<set name="soulshots" value="2"/>
		<set name="spiritshots" value="2"/>
		<set name="rnd_dam" value="10"/>
		<equip>
			<slot id="RIGHT_HAND"/>
		</equip>
		<skills>
			<skill id="100011" level="2"/>
		</skills>
		<for>
			<add stat="pAtk" order="0x10" value="689"/>
			<add stat="mAtk" order="0x10" value="114"/>
			<set stat="basePAtkSpd" order="0x08" value="379"/>
			<set stat="basePCritRate" order="0x08" value="80"/>
		</for>
	</weapon>
	<weapon id="101159" name="Dark Legion's Edge Lv.3">
		<set name="grind_commission" value="3111150"/>
		<set name="grind_point" value="10370500"/>
		<set name="variation_group_id" value="1"/>
		<set name="damage_range" value="0;0;40;120"/>
		<set name="crystal_count" value="1659"/>
		<set name="crystal_type" value="S"/>
		<set name="variation_group_id" value="1"/>
		<set name="icon" value="icon.weapon_dark_legions_edge_i00"/>
		
		<set name="type" value="SWORD"/>
		<set name="weight" value="1320"/>
		<set name="soulshots" value="2"/>
		<set name="spiritshots" value="2"/>
		<set name="rnd_dam" value="10"/>
		<equip>
			<slot id="RIGHT_HAND"/>
		</equip>
		<skills>
			<skill id="100011" level="3"/>
		</skills>
		<for>
			<add stat="pAtk" order="0x10" value="847"/>
			<add stat="mAtk" order="0x10" value="114"/>
			<set stat="basePAtkSpd" order="0x08" value="379"/>
			<set stat="basePCritRate" order="0x08" value="80"/>
		</for>
	</weapon>
	<weapon id="101160" name="Dragon Slayer Lv.1">
		<set name="grind_commission" value="3111150"/>
		<set name="grind_point" value="10370500"/>
		<set name="variation_group_id" value="1"/>
		<set name="damage_range" value="0;0;46;120"/>
		<set name="crystal_count" value="1659"/>
		<set name="crystal_type" value="S"/>
		<set name="variation_group_id" value="1"/>
		<set name="icon" value="icon.weapon_dragon_slayer_i00"/>
		
		<set name="type" value="BIGSWORD"/>
		<set name="weight" value="1840"/>
		<set name="soulshots" value="2"/>
		<set name="spiritshots" value="2"/>
		<set name="rnd_dam" value="10"/>
		<equip>
			<slot id="LEFT_RIGHT_HAND"/>
		</equip>
		<skills>
			<skill id="100011" level="1"/>
		</skills>
		<for>
			<add stat="pAtk" order="0x10" value="592"/>
			<add stat="mAtk" order="0x10" value="114"/>
			<set stat="basePAtkSpd" order="0x08" value="325"/>
			<set stat="basePCritRate" order="0x08" value="80"/>
		</for>
	</weapon>
	<weapon id="101161" name="Dragon Slayer Lv.2">
		<set name="grind_commission" value="3111150"/>
		<set name="grind_point" value="10370500"/>
		<set name="variation_group_id" value="1"/>
		<set name="damage_range" value="0;0;46;120"/>
		<set name="crystal_count" value="1659"/>
		<set name="crystal_type" value="S"/>
		<set name="variation_group_id" value="1"/>
		<set name="icon" value="icon.weapon_dragon_slayer_i00"/>
		
		<set name="type" value="BIGSWORD"/>
		<set name="weight" value="1840"/>
		<set name="soulshots" value="2"/>
		<set name="spiritshots" value="2"/>
		<set name="rnd_dam" value="10"/>
		<equip>
			<slot id="LEFT_RIGHT_HAND"/>
		</equip>
		<skills>
			<skill id="100011" level="2"/>
		</skills>
		<for>
			<add stat="pAtk" order="0x10" value="750"/>
			<add stat="mAtk" order="0x10" value="114"/>
			<set stat="basePAtkSpd" order="0x08" value="325"/>
			<set stat="basePCritRate" order="0x08" value="80"/>
		</for>
	</weapon>
	<weapon id="101162" name="Dragon Slayer Lv.3">
		<set name="grind_commission" value="3111150"/>
		<set name="grind_point" value="10370500"/>
		<set name="variation_group_id" value="1"/>
		<set name="damage_range" value="0;0;46;120"/>
		<set name="crystal_count" value="1659"/>
		<set name="crystal_type" value="S"/>
		<set name="variation_group_id" value="1"/>
		<set name="icon" value="icon.weapon_dragon_slayer_i00"/>
		
		<set name="type" value="BIGSWORD"/>
		<set name="weight" value="1840"/>
		<set name="soulshots" value="2"/>
		<set name="spiritshots" value="2"/>
		<set name="rnd_dam" value="10"/>
		<equip>
			<slot id="LEFT_RIGHT_HAND"/>
		</equip>
		<skills>
			<skill id="100011" level="3"/>
		</skills>
		<for>
			<add stat="pAtk" order="0x10" value="908"/>
			<add stat="mAtk" order="0x10" value="114"/>
			<set stat="basePAtkSpd" order="0x08" value="325"/>
			<set stat="basePCritRate" order="0x08" value="80"/>
		</for>
	</weapon>
	<weapon id="101163" name="Elysian Lv.1">
		<set name="grind_commission" value="3111150"/>
		<set name="grind_point" value="10370500"/>
		<set name="variation_group_id" value="1"/>
		<set name="damage_range" value="0;0;40;120"/>
		<set name="crystal_count" value="1659"/>
		<set name="crystal_type" value="S"/>
		<set name="variation_group_id" value="1"/>
		<set name="icon" value="icon.weapon_elysian_i00"/>
		
		<set name="type" value="BLUNT"/>
		<set name="weight" value="1580"/>
		<set name="soulshots" value="2"/>
		<set name="spiritshots" value="2"/>
		<set name="rnd_dam" value="20"/>
		<equip>
			<slot id="RIGHT_HAND"/>
		</equip>
		<skills>
			<skill id="100011" level="1"/>
		</skills>
		<for>
			<add stat="pAtk" order="0x10" value="531"/>
			<add stat="mAtk" order="0x10" value="114"/>
			<set stat="basePAtkSpd" order="0x08" value="379"/>
			<set stat="basePCritRate" order="0x08" value="60"/>
			<add stat="pAccCombat" order="0x10" value="8"/>
		</for>
	</weapon>
	<weapon id="101164" name="Elysian Lv.2">
		<set name="grind_commission" value="3111150"/>
		<set name="grind_point" value="10370500"/>
		<set name="variation_group_id" value="1"/>
		<set name="damage_range" value="0;0;40;120"/>
		<set name="crystal_count" value="1659"/>
		<set name="crystal_type" value="S"/>
		<set name="variation_group_id" value="1"/>
		<set name="icon" value="icon.weapon_elysian_i00"/>
		
		<set name="type" value="BLUNT"/>
		<set name="weight" value="1580"/>
		<set name="soulshots" value="2"/>
		<set name="spiritshots" value="2"/>
		<set name="rnd_dam" value="20"/>
		<equip>
			<slot id="RIGHT_HAND"/>
		</equip>
		<skills>
			<skill id="100011" level="2"/>
		</skills>
		<for>
			<add stat="pAtk" order="0x10" value="689"/>
			<add stat="mAtk" order="0x10" value="114"/>
			<set stat="basePAtkSpd" order="0x08" value="379"/>
			<set stat="basePCritRate" order="0x08" value="60"/>
			<add stat="pAccCombat" order="0x10" value="8"/>
		</for>
	</weapon>
	<weapon id="101165" name="Elysian Lv.3">
		<set name="grind_commission" value="3111150"/>
		<set name="grind_point" value="10370500"/>
		<set name="variation_group_id" value="1"/>
		<set name="damage_range" value="0;0;40;120"/>
		<set name="crystal_count" value="1659"/>
		<set name="crystal_type" value="S"/>
		<set name="variation_group_id" value="1"/>
		<set name="icon" value="icon.weapon_elysian_i00"/>
		
		<set name="type" value="BLUNT"/>
		<set name="weight" value="1580"/>
		<set name="soulshots" value="2"/>
		<set name="spiritshots" value="2"/>
		<set name="rnd_dam" value="20"/>
		<equip>
			<slot id="RIGHT_HAND"/>
		</equip>
		<skills>
			<skill id="100011" level="3"/>
		</skills>
		<for>
			<add stat="pAtk" order="0x10" value="847"/>
			<add stat="mAtk" order="0x10" value="114"/>
			<set stat="basePAtkSpd" order="0x08" value="379"/>
			<set stat="basePCritRate" order="0x08" value="60"/>
			<add stat="pAccCombat" order="0x10" value="8"/>
		</for>
	</weapon>
	<weapon id="101166" name="Behemoth' Tuning Fork Lv.1">
		<set name="grind_commission" value="4045260"/>
		<set name="grind_point" value="13484200"/>
		<set name="variation_group_id" value="1"/>
		<set name="damage_range" value="0;0;44;120"/>
		<set name="crystal_count" value="2157"/>
		<set name="crystal_type" value="S"/>
		<set name="variation_group_id" value="1"/>
		<set name="icon" value="icon.weapon_tuning_fork_of_behemoth_i00"/>
		
		<set name="type" value="BIGBLUNT"/>
		<set name="weight" value="1890"/>
		<set name="soulshots" value="2"/>
		<set name="spiritshots" value="2"/>
		<set name="rnd_dam" value="20"/>
		<equip>
			<slot id="LEFT_RIGHT_HAND"/>
		</equip>
		<skills>
			<skill id="100011" level="1"/>
		</skills>
		<for>
			<add stat="pAtk" order="0x10" value="592"/>
			<add stat="mAtk" order="0x10" value="121"/>
			<set stat="basePAtkSpd" order="0x08" value="325"/>
			<set stat="basePCritRate" order="0x08" value="60"/>
			<add stat="pAccCombat" order="0x10" value="8"/>
		</for>
	</weapon>
	<weapon id="101167" name="Behemoth' Tuning Fork Lv.2">
		<set name="grind_commission" value="4045260"/>
		<set name="grind_point" value="13484200"/>
		<set name="variation_group_id" value="1"/>
		<set name="damage_range" value="0;0;44;120"/>
		<set name="crystal_count" value="2157"/>
		<set name="crystal_type" value="S"/>
		<set name="variation_group_id" value="1"/>
		<set name="icon" value="icon.weapon_tuning_fork_of_behemoth_i00"/>
		
		<set name="type" value="BIGBLUNT"/>
		<set name="weight" value="1890"/>
		<set name="soulshots" value="2"/>
		<set name="spiritshots" value="2"/>
		<set name="rnd_dam" value="20"/>
		<equip>
			<slot id="LEFT_RIGHT_HAND"/>
		</equip>
		<skills>
			<skill id="100011" level="2"/>
		</skills>
		<for>
			<add stat="pAtk" order="0x10" value="750"/>
			<add stat="mAtk" order="0x10" value="121"/>
			<set stat="basePAtkSpd" order="0x08" value="325"/>
			<set stat="basePCritRate" order="0x08" value="60"/>
			<add stat="pAccCombat" order="0x10" value="8"/>
		</for>
	</weapon>
	<weapon id="101168" name="Behemoth' Tuning Fork Lv.3">
		<set name="grind_commission" value="4045260"/>
		<set name="grind_point" value="13484200"/>
		<set name="variation_group_id" value="1"/>
		<set name="damage_range" value="0;0;44;120"/>
		<set name="crystal_count" value="2157"/>
		<set name="crystal_type" value="S"/>
		<set name="variation_group_id" value="1"/>
		<set name="icon" value="icon.weapon_tuning_fork_of_behemoth_i00"/>
		
		<set name="type" value="BIGBLUNT"/>
		<set name="weight" value="1890"/>
		<set name="soulshots" value="2"/>
		<set name="spiritshots" value="2"/>
		<set name="rnd_dam" value="20"/>
		<equip>
			<slot id="LEFT_RIGHT_HAND"/>
		</equip>
		<skills>
			<skill id="100011" level="3"/>
		</skills>
		<for>
			<add stat="pAtk" order="0x10" value="908"/>
			<add stat="mAtk" order="0x10" value="121"/>
			<set stat="basePAtkSpd" order="0x08" value="325"/>
			<set stat="basePCritRate" order="0x08" value="60"/>
			<add stat="pAccCombat" order="0x10" value="8"/>
		</for>
	</weapon>
	<weapon id="101169" name="Soul Separator Lv.1">
		<set name="grind_commission" value="3111150"/>
		<set name="grind_point" value="10370500"/>
		<set name="variation_group_id" value="1"/>
		<set name="damage_range" value="0;0;40;120"/>
		<set name="crystal_count" value="1659"/>
		<set name="crystal_type" value="S"/>
		<set name="variation_group_id" value="1"/>
		<set name="icon" value="icon.weapon_soul_separator_i00"/>
		
		<set name="type" value="DAGGER"/>
		<set name="weight" value="950"/>
		<set name="soulshots" value="2"/>
		<set name="spiritshots" value="2"/>
		<set name="rnd_dam" value="5"/>
		<equip>
			<slot id="RIGHT_HAND"/>
		</equip>
		<skills>
			<skill id="100011" level="1"/>
		</skills>
		<for>
			<add stat="pAtk" order="0x10" value="496"/>
			<add stat="mAtk" order="0x10" value="114"/>
			<set stat="basePAtkSpd" order="0x08" value="433"/>
			<set stat="basePCritRate" order="0x08" value="120"/>
			<add stat="pAccCombat" order="0x10" value="-3.75"/>
		</for>
	</weapon>
	<weapon id="101170" name="Soul Separator Lv.2">
		<set name="grind_commission" value="3111150"/>
		<set name="grind_point" value="10370500"/>
		<set name="variation_group_id" value="1"/>
		<set name="damage_range" value="0;0;40;120"/>
		<set name="crystal_count" value="1659"/>
		<set name="crystal_type" value="S"/>
		<set name="variation_group_id" value="1"/>
		<set name="icon" value="icon.weapon_soul_separator_i00"/>
		
		<set name="type" value="DAGGER"/>
		<set name="weight" value="950"/>
		<set name="soulshots" value="2"/>
		<set name="spiritshots" value="2"/>
		<set name="rnd_dam" value="5"/>
		<equip>
			<slot id="RIGHT_HAND"/>
		</equip>
		<skills>
			<skill id="100011" level="2"/>
		</skills>
		<for>
			<add stat="pAtk" order="0x10" value="654"/>
			<add stat="mAtk" order="0x10" value="114"/>
			<set stat="basePAtkSpd" order="0x08" value="433"/>
			<set stat="basePCritRate" order="0x08" value="120"/>
			<add stat="pAccCombat" order="0x10" value="-3.75"/>
		</for>
	</weapon>
	<weapon id="101171" name="Soul Separator Lv.3">
		<set name="grind_commission" value="3111150"/>
		<set name="grind_point" value="10370500"/>
		<set name="variation_group_id" value="1"/>
		<set name="damage_range" value="0;0;40;120"/>
		<set name="crystal_count" value="1659"/>
		<set name="crystal_type" value="S"/>
		<set name="variation_group_id" value="1"/>
		<set name="icon" value="icon.weapon_soul_separator_i00"/>
		
		<set name="type" value="DAGGER"/>
		<set name="weight" value="950"/>
		<set name="soulshots" value="2"/>
		<set name="spiritshots" value="2"/>
		<set name="rnd_dam" value="5"/>
		<equip>
			<slot id="RIGHT_HAND"/>
		</equip>
		<skills>
			<skill id="100011" level="3"/>
		</skills>
		<for>
			<add stat="pAtk" order="0x10" value="812"/>
			<add stat="mAtk" order="0x10" value="114"/>
			<set stat="basePAtkSpd" order="0x08" value="433"/>
			<set stat="basePCritRate" order="0x08" value="120"/>
			<add stat="pAccCombat" order="0x10" value="-3.75"/>
		</for>
	</weapon>
	<weapon id="101172" name="Dragon Grinder Lv.1">
		<set name="grind_commission" value="3111150"/>
		<set name="grind_point" value="10370500"/>
		<set name="variation_group_id" value="1"/>
		<set name="damage_range" value="0;0;32;120"/>
		<set name="crystal_count" value="1659"/>
		<set name="crystal_type" value="S"/>
		<set name="variation_group_id" value="1"/>
		<set name="icon" value="icon.weapon_dragon_grinder_i00"/>
		
		<set name="type" value="DUALFIST"/>
		<set name="weight" value="1350"/>
		<set name="soulshots" value="2"/>
		<set name="spiritshots" value="2"/>
		<set name="rnd_dam" value="5"/>
		<equip>
			<slot id="LEFT_RIGHT_HAND"/>
		</equip>
		<skills>
			<skill id="100011" level="1"/>
		</skills>
		<for>
			<add stat="pAtk" order="0x10" value="592"/>
			<add stat="mAtk" order="0x10" value="114"/>
			<set stat="basePAtkSpd" order="0x08" value="325"/>
			<set stat="basePCritRate" order="0x08" value="60"/>
			<add stat="pAccCombat" order="0x10" value="8"/>
		</for>
	</weapon>
	<weapon id="101173" name="Dragon Grinder Lv.2">
		<set name="grind_commission" value="3111150"/>
		<set name="grind_point" value="10370500"/>
		<set name="variation_group_id" value="1"/>
		<set name="damage_range" value="0;0;32;120"/>
		<set name="crystal_count" value="1659"/>
		<set name="crystal_type" value="S"/>
		<set name="variation_group_id" value="1"/>
		<set name="icon" value="icon.weapon_dragon_grinder_i00"/>
		
		<set name="type" value="DUALFIST"/>
		<set name="weight" value="1350"/>
		<set name="soulshots" value="2"/>
		<set name="spiritshots" value="2"/>
		<set name="rnd_dam" value="5"/>
		<equip>
			<slot id="LEFT_RIGHT_HAND"/>
		</equip>
		<skills>
			<skill id="100011" level="2"/>
		</skills>
		<for>
			<add stat="pAtk" order="0x10" value="750"/>
			<add stat="mAtk" order="0x10" value="114"/>
			<set stat="basePAtkSpd" order="0x08" value="325"/>
			<set stat="basePCritRate" order="0x08" value="60"/>
			<add stat="pAccCombat" order="0x10" value="8"/>
		</for>
	</weapon>
	<weapon id="101174" name="Dragon Grinder Lv.3">
		<set name="grind_commission" value="3111150"/>
		<set name="grind_point" value="10370500"/>
		<set name="variation_group_id" value="1"/>
		<set name="damage_range" value="0;0;32;120"/>
		<set name="crystal_count" value="1659"/>
		<set name="crystal_type" value="S"/>
		<set name="variation_group_id" value="1"/>
		<set name="icon" value="icon.weapon_dragon_grinder_i00"/>
		
		<set name="type" value="DUALFIST"/>
		<set name="weight" value="1350"/>
		<set name="soulshots" value="2"/>
		<set name="spiritshots" value="2"/>
		<set name="rnd_dam" value="5"/>
		<equip>
			<slot id="LEFT_RIGHT_HAND"/>
		</equip>
		<skills>
			<skill id="100011" level="3"/>
		</skills>
		<for>
			<add stat="pAtk" order="0x10" value="908"/>
			<add stat="mAtk" order="0x10" value="114"/>
			<set stat="basePAtkSpd" order="0x08" value="325"/>
			<set stat="basePCritRate" order="0x08" value="60"/>
			<add stat="pAccCombat" order="0x10" value="8"/>
		</for>
	</weapon>
	<weapon id="101175" name="Tiphon's Spear Lv.1">
		<set name="grind_commission" value="4045260"/>
		<set name="grind_point" value="13484200"/>
		<set name="variation_group_id" value="1"/>
		<set name="damage_range" value="0;0;66;120"/>
		<set name="crystal_count" value="2157"/>
		<set name="crystal_type" value="S"/>
		<set name="variation_group_id" value="1"/>
		<set name="icon" value="icon.weapon_tiphon_spear_i00"/>
		
		<set name="type" value="POLE"/>
		<set name="weight" value="1820"/>
		<set name="soulshots" value="2"/>
		<set name="spiritshots" value="2"/>
		<set name="rnd_dam" value="10"/>
		<equip>
			<slot id="LEFT_RIGHT_HAND"/>
		</equip>
		<skills>
			<skill id="100011" level="1"/>
		</skills>
		<for>
			<add stat="pAtk" order="0x10" value="531"/>
			<add stat="mAtk" order="0x10" value="121"/>
			<set stat="basePAtkSpd" order="0x08" value="325"/>
			<set stat="basePCritRate" order="0x08" value="80"/>
			<add stat="pAccCombat" order="0x10" value="-3.75"/>
		</for>
	</weapon>
	<weapon id="101176" name="Tiphon's Spear Lv.2">
		<set name="grind_commission" value="4045260"/>
		<set name="grind_point" value="13484200"/>
		<set name="variation_group_id" value="1"/>
		<set name="damage_range" value="0;0;66;120"/>
		<set name="crystal_count" value="2157"/>
		<set name="crystal_type" value="S"/>
		<set name="variation_group_id" value="1"/>
		<set name="icon" value="icon.weapon_tiphon_spear_i00"/>
		
		<set name="type" value="POLE"/>
		<set name="weight" value="1820"/>
		<set name="soulshots" value="2"/>
		<set name="spiritshots" value="2"/>
		<set name="rnd_dam" value="10"/>
		<equip>
			<slot id="LEFT_RIGHT_HAND"/>
		</equip>
		<skills>
			<skill id="100011" level="2"/>
		</skills>
		<for>
			<add stat="pAtk" order="0x10" value="689"/>
			<add stat="mAtk" order="0x10" value="121"/>
			<set stat="basePAtkSpd" order="0x08" value="325"/>
			<set stat="basePCritRate" order="0x08" value="80"/>
			<add stat="pAccCombat" order="0x10" value="-3.75"/>
		</for>
	</weapon>
	<weapon id="101177" name="Tiphon's Spear Lv.3">
		<set name="grind_commission" value="4045260"/>
		<set name="grind_point" value="13484200"/>
		<set name="variation_group_id" value="1"/>
		<set name="damage_range" value="0;0;66;120"/>
		<set name="crystal_count" value="2157"/>
		<set name="crystal_type" value="S"/>
		<set name="variation_group_id" value="1"/>
		<set name="icon" value="icon.weapon_tiphon_spear_i00"/>
		
		<set name="type" value="POLE"/>
		<set name="weight" value="1820"/>
		<set name="soulshots" value="2"/>
		<set name="spiritshots" value="2"/>
		<set name="rnd_dam" value="10"/>
		<equip>
			<slot id="LEFT_RIGHT_HAND"/>
		</equip>
		<skills>
			<skill id="100011" level="3"/>
		</skills>
		<for>
			<add stat="pAtk" order="0x10" value="847"/>
			<add stat="mAtk" order="0x10" value="121"/>
			<set stat="basePAtkSpd" order="0x08" value="325"/>
			<set stat="basePCritRate" order="0x08" value="80"/>
			<add stat="pAccCombat" order="0x10" value="-3.75"/>
		</for>
	</weapon>
	<weapon id="101178" name="Damascus*Damascus Lv.1">
		<set name="grind_commission" value="3111150"/>
		<set name="grind_point" value="10370500"/>
		<set name="variation_group_id" value="1"/>
		<set name="damage_range" value="0;0;44;120"/>
		<set name="crystal_count" value="1659"/>
		<set name="crystal_type" value="S"/>
		<set name="variation_group_id" value="1"/>
		<set name="icon" value="icon.weapon_dual_sword_i00"/>
		
		<set name="type" value="DUAL"/>
		<set name="weight" value="2080"/>
		<set name="soulshots" value="2"/>
		<set name="spiritshots" value="2"/>
		<set name="rnd_dam" value="10"/>
		<equip>
			<slot id="LEFT_RIGHT_HAND"/>
		</equip>
		<skills>
			<skill id="100011" level="1"/>
		</skills>
		<for>
			<add stat="pAtk" order="0x10" value="592"/>
			<add stat="mAtk" order="0x10" value="114"/>
			<set stat="basePAtkSpd" order="0x08" value="325"/>
			<set stat="basePCritRate" order="0x08" value="80"/>
		</for>
	</weapon>
	<weapon id="101179" name="Damascus*Damascus Lv.2">
		<set name="grind_commission" value="3111150"/>
		<set name="grind_point" value="10370500"/>
		<set name="variation_group_id" value="1"/>
		<set name="damage_range" value="0;0;44;120"/>
		<set name="crystal_count" value="1659"/>
		<set name="crystal_type" value="S"/>
		<set name="variation_group_id" value="1"/>
		<set name="icon" value="icon.weapon_dual_sword_i00"/>
		
		<set name="type" value="DUAL"/>
		<set name="weight" value="2080"/>
		<set name="soulshots" value="2"/>
		<set name="spiritshots" value="2"/>
		<set name="rnd_dam" value="10"/>
		<equip>
			<slot id="LEFT_RIGHT_HAND"/>
		</equip>
		<skills>
			<skill id="100011" level="2"/>
		</skills>
		<for>
			<add stat="pAtk" order="0x10" value="750"/>
			<add stat="mAtk" order="0x10" value="114"/>
			<set stat="basePAtkSpd" order="0x08" value="325"/>
			<set stat="basePCritRate" order="0x08" value="80"/>
		</for>
	</weapon>
	<weapon id="101180" name="Damascus*Damascus Lv.3">
		<set name="grind_commission" value="3111150"/>
		<set name="grind_point" value="10370500"/>
		<set name="variation_group_id" value="1"/>
		<set name="damage_range" value="0;0;44;120"/>
		<set name="crystal_count" value="1659"/>
		<set name="crystal_type" value="S"/>
		<set name="variation_group_id" value="1"/>
		<set name="icon" value="icon.weapon_dual_sword_i00"/>
		
		<set name="type" value="DUAL"/>
		<set name="weight" value="2080"/>
		<set name="soulshots" value="2"/>
		<set name="spiritshots" value="2"/>
		<set name="rnd_dam" value="10"/>
		<equip>
			<slot id="LEFT_RIGHT_HAND"/>
		</equip>
		<skills>
			<skill id="100011" level="3"/>
		</skills>
		<for>
			<add stat="pAtk" order="0x10" value="908"/>
			<add stat="mAtk" order="0x10" value="114"/>
			<set stat="basePAtkSpd" order="0x08" value="325"/>
			<set stat="basePCritRate" order="0x08" value="80"/>
		</for>
	</weapon>
	<weapon id="101181" name="Carnage Bow Lv.1">
		<set name="grind_commission" value="2114700"/>
		<set name="grind_point" value="7049000"/>
		<set name="reuse_delay" value="1500"/>
		<set name="variation_group_id" value="1"/>
		<set name="damage_range" value="0;0;10;0"/>
		<set name="crystal_count" value="1128"/>
		<set name="crystal_type" value="S"/>
		<set name="variation_group_id" value="1"/>
		<set name="icon" value="icon.weapon_carnium_bow_i00"/>
		
		<set name="type" value="BOW"/>
		<set name="weight" value="1670"/>
		<set name="soulshots" value="3"/>
		<set name="spiritshots" value="2"/>
		<set name="rnd_dam" value="5"/>
		<set name="mp_consume" value="5"/>
		<equip>
			<slot id="LEFT_RIGHT_HAND"/>
		</equip>
		<skills>
			<skill id="100011" level="1"/>
		</skills>
		<for>
			<add stat="pAtk" order="0x10" value="1000"/>
			<add stat="mAtk" order="0x10" value="107"/>
			<set stat="basePAtkSpd" order="0x08" value="293"/>
			<set stat="basePCritRate" order="0x08" value="120"/>
			<add stat="pAccCombat" order="0x10" value="-3.75"/>
		</for>
	</weapon>
	<weapon id="101182" name="Carnage Bow Lv.2">
		<set name="grind_commission" value="2114700"/>
		<set name="grind_point" value="7049000"/>
		<set name="reuse_delay" value="1500"/>
		<set name="variation_group_id" value="1"/>
		<set name="damage_range" value="0;0;10;0"/>
		<set name="crystal_count" value="1128"/>
		<set name="crystal_type" value="S"/>
		<set name="variation_group_id" value="1"/>
		<set name="icon" value="icon.weapon_carnium_bow_i00"/>
		
		<set name="type" value="BOW"/>
		<set name="weight" value="1670"/>
		<set name="soulshots" value="3"/>
		<set name="spiritshots" value="2"/>
		<set name="rnd_dam" value="5"/>
		<set name="mp_consume" value="5"/>
		<equip>
			<slot id="LEFT_RIGHT_HAND"/>
		</equip>
		<skills>
			<skill id="100011" level="2"/>
		</skills>
		<for>
			<add stat="pAtk" order="0x10" value="1150"/>
			<add stat="mAtk" order="0x10" value="107"/>
			<set stat="basePAtkSpd" order="0x08" value="293"/>
			<set stat="basePCritRate" order="0x08" value="120"/>
			<add stat="pAccCombat" order="0x10" value="-3.75"/>
		</for>
	</weapon>
	<weapon id="101183" name="Carnage Bow Lv.3">
		<set name="grind_commission" value="2114700"/>
		<set name="grind_point" value="7049000"/>
		<set name="reuse_delay" value="1500"/>
		<set name="variation_group_id" value="1"/>
		<set name="damage_range" value="0;0;10;0"/>
		<set name="crystal_count" value="1128"/>
		<set name="crystal_type" value="S"/>
		<set name="variation_group_id" value="1"/>
		<set name="icon" value="icon.weapon_carnium_bow_i00"/>
		
		<set name="type" value="BOW"/>
		<set name="weight" value="1670"/>
		<set name="soulshots" value="3"/>
		<set name="spiritshots" value="2"/>
		<set name="rnd_dam" value="5"/>
		<set name="mp_consume" value="5"/>
		<equip>
			<slot id="LEFT_RIGHT_HAND"/>
		</equip>
		<skills>
			<skill id="100011" level="3"/>
		</skills>
		<for>
			<add stat="pAtk" order="0x10" value="1300"/>
			<add stat="mAtk" order="0x10" value="107"/>
			<set stat="basePAtkSpd" order="0x08" value="293"/>
			<set stat="basePCritRate" order="0x08" value="120"/>
			<add stat="pAccCombat" order="0x10" value="-3.75"/>
		</for>
	</weapon>
	<weapon id="101184" name="Sword of Miracles Lv.1">
		<set name="grind_commission" value="3111150"/>
		<set name="grind_point" value="10370500"/>
		<set name="variation_group_id" value="1"/>
		<set name="damage_range" value="0;0;40;120"/>
		<set name="crystal_count" value="1659"/>
		<set name="crystal_type" value="S"/>
		<set name="variation_group_id" value="1"/>
		<set name="icon" value="icon.weapon_sword_of_miracle_i00"/>
		
		<set name="type" value="SWORD"/>
		<set name="weight" value="840"/>
		<set name="soulshots" value="2"/>
		<set name="spiritshots" value="2"/>
		<set name="rnd_dam" value="10"/>
		<set name="is_magic_weapon" value="true"/>
		<equip>
			<slot id="RIGHT_HAND"/>
		</equip>
		<skills>
			<skill id="100012" level="1"/>
		</skills>
		<for>
			<add stat="pAtk" order="0x10" value="186"/>
			<add stat="mAtk" order="0x10" value="1025"/>
			<set stat="basePAtkSpd" order="0x08" value="379"/>
			<set stat="basePCritRate" order="0x08" value="80"/>
		</for>
	</weapon>
	<weapon id="101185" name="Sword of Miracles Lv.2">
		<set name="grind_commission" value="3111150"/>
		<set name="grind_point" value="10370500"/>
		<set name="variation_group_id" value="1"/>
		<set name="damage_range" value="0;0;40;120"/>
		<set name="crystal_count" value="1659"/>
		<set name="crystal_type" value="S"/>
		<set name="variation_group_id" value="1"/>
		<set name="icon" value="icon.weapon_sword_of_miracle_i00"/>
		
		<set name="type" value="SWORD"/>
		<set name="weight" value="840"/>
		<set name="soulshots" value="2"/>
		<set name="spiritshots" value="2"/>
		<set name="rnd_dam" value="10"/>
		<set name="is_magic_weapon" value="true"/>
		<equip>
			<slot id="RIGHT_HAND"/>
		</equip>
		<skills>
			<skill id="100012" level="2"/>
		</skills>
		<for>
			<add stat="pAtk" order="0x10" value="186"/>
			<add stat="mAtk" order="0x10" value="1183"/>
			<set stat="basePAtkSpd" order="0x08" value="379"/>
			<set stat="basePCritRate" order="0x08" value="80"/>
		</for>
	</weapon>
	<weapon id="101186" name="Sword of Miracles Lv.3">
		<set name="grind_commission" value="3111150"/>
		<set name="grind_point" value="10370500"/>
		<set name="variation_group_id" value="1"/>
		<set name="damage_range" value="0;0;40;120"/>
		<set name="crystal_count" value="1659"/>
		<set name="crystal_type" value="S"/>
		<set name="variation_group_id" value="1"/>
		<set name="icon" value="icon.weapon_sword_of_miracle_i00"/>
		
		<set name="type" value="SWORD"/>
		<set name="weight" value="840"/>
		<set name="soulshots" value="2"/>
		<set name="spiritshots" value="2"/>
		<set name="rnd_dam" value="10"/>
		<set name="is_magic_weapon" value="true"/>
		<equip>
			<slot id="RIGHT_HAND"/>
		</equip>
		<skills>
			<skill id="100012" level="3"/>
		</skills>
		<for>
			<add stat="pAtk" order="0x10" value="186"/>
			<add stat="mAtk" order="0x10" value="1341"/>
			<set stat="basePAtkSpd" order="0x08" value="379"/>
			<set stat="basePCritRate" order="0x08" value="80"/>
		</for>
	</weapon>
	<weapon id="101187" name="Daimon Crystal Lv.1">
		<set name="grind_commission" value="4045260"/>
		<set name="grind_point" value="13484200"/>
		<set name="variation_group_id" value="1"/>
		<set name="damage_range" value="0;0;40;120"/>
		<set name="crystal_count" value="2157"/>
		<set name="crystal_type" value="S"/>
		<set name="variation_group_id" value="1"/>
		<set name="icon" value="icon.weapon_crystal_of_deamon_i00"/>
		
		<set name="type" value="BIGBLUNT"/>
		<set name="weight" value="880"/>
		<set name="soulshots" value="2"/>
		<set name="spiritshots" value="2"/>
		<set name="rnd_dam" value="20"/>
		<set name="is_magic_weapon" value="true"/>
		<equip>
			<slot id="LEFT_RIGHT_HAND"/>
		</equip>
		<skills>
			<skill id="100012" level="1"/>
		</skills>
		<for>
			<add stat="pAtk" order="0x10" value="245"/>
			<add stat="mAtk" order="0x10" value="1043"/>
			<set stat="basePAtkSpd" order="0x08" value="325"/>
			<set stat="basePCritRate" order="0x08" value="60"/>
			<add stat="pAccCombat" order="0x10" value="8"/>
		</for>
	</weapon>
	<weapon id="101188" name="Daimon Crystal Lv.2">
		<set name="grind_commission" value="4045260"/>
		<set name="grind_point" value="13484200"/>
		<set name="variation_group_id" value="1"/>
		<set name="damage_range" value="0;0;40;120"/>
		<set name="crystal_count" value="2157"/>
		<set name="crystal_type" value="S"/>
		<set name="variation_group_id" value="1"/>
		<set name="icon" value="icon.weapon_crystal_of_deamon_i00"/>
		
		<set name="type" value="BIGBLUNT"/>
		<set name="weight" value="880"/>
		<set name="soulshots" value="2"/>
		<set name="spiritshots" value="2"/>
		<set name="rnd_dam" value="20"/>
		<set name="is_magic_weapon" value="true"/>
		<equip>
			<slot id="LEFT_RIGHT_HAND"/>
		</equip>
		<skills>
			<skill id="100012" level="2"/>
		</skills>
		<for>
			<add stat="pAtk" order="0x10" value="245"/>
			<add stat="mAtk" order="0x10" value="1201"/>
			<set stat="basePAtkSpd" order="0x08" value="325"/>
			<set stat="basePCritRate" order="0x08" value="60"/>
			<add stat="pAccCombat" order="0x10" value="8"/>
		</for>
	</weapon>
	<weapon id="101189" name="Daimon Crystal Lv.3">
		<set name="grind_commission" value="4045260"/>
		<set name="grind_point" value="13484200"/>
		<set name="variation_group_id" value="1"/>
		<set name="damage_range" value="0;0;40;120"/>
		<set name="crystal_count" value="2157"/>
		<set name="crystal_type" value="S"/>
		<set name="variation_group_id" value="1"/>
		<set name="icon" value="icon.weapon_crystal_of_deamon_i00"/>
		
		<set name="type" value="BIGBLUNT"/>
		<set name="weight" value="880"/>
		<set name="soulshots" value="2"/>
		<set name="spiritshots" value="2"/>
		<set name="rnd_dam" value="20"/>
		<set name="is_magic_weapon" value="true"/>
		<equip>
			<slot id="LEFT_RIGHT_HAND"/>
		</equip>
		<skills>
			<skill id="100012" level="3"/>
		</skills>
		<for>
			<add stat="pAtk" order="0x10" value="245"/>
			<add stat="mAtk" order="0x10" value="1359"/>
			<set stat="basePAtkSpd" order="0x08" value="325"/>
			<set stat="basePCritRate" order="0x08" value="60"/>
			<add stat="pAccCombat" order="0x10" value="8"/>
		</for>
	</weapon>
	<weapon id="101190" name="Double Yaksa Mace Lv.1">
		<set name="grind_commission" value="919500"/>
		<set name="grind_point" value="3065000"/>
		<set name="variation_group_id" value="1"/>
		<set name="damage_range" value="0;0;40;120"/>
		<set name="crystal_count" value="2452"/>
		<set name="crystal_type" value="S"/>
		<set name="variation_group_id" value="1"/>
		<set name="icon" value="icon.weapon_yaksa_mace_i00"/>
		
		<set name="rnd_dam" value="20"/>
		<set name="soulshots" value="1"/>
		<set name="spiritshots" value="1"/>
		<set name="type" value="DUALBLUNT"/>
		<set name="weight" value="1640"/>
		<equip>
			<slot id="LEFT_RIGHT_HAND"/>
		</equip>
		<skills>
			<skill id="100011" level="1"/>
		</skills>
		<for>
			<add stat="pAtk" order="0x10" value="592"/>
			<add stat="mAtk" order="0x10" value="114"/>
			<set stat="basePCritRate" order="0x08" value="60"/>
			<set stat="basePAtkSpd" order="0x08" value="325"/>
			<add stat="pAccCombat" order="0x10" value="8"/>
		</for>
	</weapon>
	<weapon id="101191" name="Double Yaksa Mace Lv.2">
		<set name="grind_commission" value="919500"/>
		<set name="grind_point" value="3065000"/>
		<set name="variation_group_id" value="1"/>
		<set name="damage_range" value="0;0;40;120"/>
		<set name="crystal_count" value="2452"/>
		<set name="crystal_type" value="S"/>
		<set name="variation_group_id" value="1"/>
		<set name="icon" value="icon.weapon_yaksa_mace_i00"/>
		
		<set name="rnd_dam" value="20"/>
		<set name="soulshots" value="1"/>
		<set name="spiritshots" value="1"/>
		<set name="type" value="DUALBLUNT"/>
		<set name="weight" value="1640"/>
		<equip>
			<slot id="LEFT_RIGHT_HAND"/>
		</equip>
		<skills>
			<skill id="100011" level="2"/>
		</skills>
		<for>
			<add stat="pAtk" order="0x10" value="750"/>
			<add stat="mAtk" order="0x10" value="114"/>
			<set stat="basePCritRate" order="0x08" value="60"/>
			<set stat="basePAtkSpd" order="0x08" value="325"/>
			<add stat="pAccCombat" order="0x10" value="8"/>
		</for>
	</weapon>
	<weapon id="101192" name="Double Yaksa Mace Lv.3">
		<set name="grind_commission" value="919500"/>
		<set name="grind_point" value="3065000"/>
		<set name="variation_group_id" value="1"/>
		<set name="damage_range" value="0;0;40;120"/>
		<set name="crystal_count" value="2452"/>
		<set name="crystal_type" value="S"/>
		<set name="variation_group_id" value="1"/>
		<set name="icon" value="icon.weapon_yaksa_mace_i00"/>
		
		<set name="rnd_dam" value="20"/>
		<set name="soulshots" value="1"/>
		<set name="spiritshots" value="1"/>
		<set name="type" value="DUALBLUNT"/>
		<set name="weight" value="1640"/>
		<equip>
			<slot id="LEFT_RIGHT_HAND"/>
		</equip>
		<skills>
			<skill id="100011" level="3"/>
		</skills>
		<for>
			<add stat="pAtk" order="0x10" value="908"/>
			<add stat="mAtk" order="0x10" value="114"/>
			<set stat="basePCritRate" order="0x08" value="60"/>
			<set stat="basePAtkSpd" order="0x08" value="325"/>
			<add stat="pAccCombat" order="0x10" value="8"/>
		</for>
	</weapon>	
</list>