<?xml version="1.0" encoding="UTF-8"?>
<!DOCTYPE list SYSTEM "multisell.dtd">
<!--AUTHOR: Bonux-->
<list>
	<config show_all="false" no_tax="true"/>
	<item>
		<production id="35079" count="1"/><!--Кровавый ПВЕ Шлем Айдиоса -->
		<ingredient id="17430" count="1"/><!--Шлем Айдиоса -->
		<ingredient id="35569" count="10"/><!--Усиливающий Камень Кровавых Доспехов -->
		<ingredient id="35562" count="60"/><!--Разрушительная Энергия -->
		<ingredient id="35563" count="40"/><!--Сила Гигантов -->
		<ingredient id="19440" count="390"/><!--Самоцвет Ранг R -->
		<ingredient id="17371" count="4685"/><!--Кристалл R -->
	</item>
	<item>
		<production id="35085" count="1"/><!--Кровавый ПВЕ кожанный Шлем Айдиоса -->
		<ingredient id="17436" count="1"/><!--Шлем Айдиоса -->
		<ingredient id="35569" count="10"/><!--Усиливающий Камень Кровавых Доспехов -->
		<ingredient id="35562" count="60"/><!--Разрушительная Энергия -->
		<ingredient id="35563" count="40"/><!--Сила Гигантов -->
		<ingredient id="19440" count="390"/><!--Самоцвет Ранг R -->
		<ingredient id="17371" count="4685"/><!--Кристалл R -->
	</item>
	<item>
		<production id="35090" count="1"/><!--Кровавый ПВЕ диадема айдиоса -->
		<ingredient id="17441" count="1"/><!--Шлем Айдиоса -->
		<ingredient id="35569" count="10"/><!--Усиливающий Камень Кровавых Доспехов -->
		<ingredient id="35562" count="60"/><!--Разрушительная Энергия -->
		<ingredient id="35563" count="40"/><!--Сила Гигантов -->
		<ingredient id="19440" count="390"/><!--Самоцвет Ранг R -->
		<ingredient id="17371" count="4685"/><!--Кристалл R -->
	</item>
	<item>
		<production id="35079" count="1"/><!--Кровавый ПВЕ Шлем Айдиоса -->
		<ingredient id="17430" count="1"/><!--Шлем Айдиоса -->
		<ingredient id="35569" count="10"/><!--Усиливающий Камень Кровавых Доспехов -->
		<ingredient id="35562" count="48"/><!--Разрушительная Энергия -->
		<ingredient id="35563" count="40"/><!--Сила Гигантов -->
		<ingredient id="19440" count="390"/><!--Самоцвет Ранг R -->
		<ingredient id="17371" count="4685"/><!--Кристалл R -->
		<ingredient id="36515" count="10"/><!--Эльсиум -->
	</item>
	<item>
		<production id="35085" count="1"/><!--Кровавый ПВЕ кожанный Шлем Айдиоса -->
		<ingredient id="17436" count="1"/><!--Шлем Айдиоса -->
		<ingredient id="35569" count="10"/><!--Усиливающий Камень Кровавых Доспехов -->
		<ingredient id="35562" count="48"/><!--Разрушительная Энергия -->
		<ingredient id="35563" count="40"/><!--Сила Гигантов -->
		<ingredient id="19440" count="390"/><!--Самоцвет Ранг R -->
		<ingredient id="17371" count="4685"/><!--Кристалл R -->
		<ingredient id="36515" count="10"/><!--Эльсиум -->
	</item>
	<item>
		<production id="35090" count="1"/><!--Кровавый ПВЕ диадема айдиоса -->
		<ingredient id="17441" count="1"/><!--Шлем Айдиоса -->
		<ingredient id="35569" count="10"/><!--Усиливающий Камень Кровавых Доспехов -->
		<ingredient id="35562" count="48"/><!--Разрушительная Энергия -->
		<ingredient id="35563" count="40"/><!--Сила Гигантов -->
		<ingredient id="19440" count="390"/><!--Самоцвет Ранг R -->
		<ingredient id="17371" count="4685"/><!--Кристалл R -->
		<ingredient id="36515" count="10"/><!--Эльсиум -->
	</item>
	<item>
		<production id="35063" count="1"/><!--Темный ПВП Шлем Айдиоса -->
		<ingredient id="17430" count="1"/><!--Шлем Айдиоса -->
		<ingredient id="35567" count="10"/><!--Усиливающий Камень Темных Доспехов -->
		<ingredient id="35562" count="60"/><!--Разрушительная Энергия -->
		<ingredient id="35563" count="40"/><!--Сила Гигантов -->
		<ingredient id="19440" count="390"/><!--Самоцвет Ранг R -->
		<ingredient id="17371" count="4685"/><!--Кристалл R -->
	</item>
	<item>
		<production id="35069" count="1"/><!--Темный ПВП кожанный Шлем Айдиоса -->
		<ingredient id="17436" count="1"/><!--Шлем Айдиоса -->
		<ingredient id="35567" count="10"/><!--Усиливающий Камень Темных Доспехов -->
		<ingredient id="35562" count="60"/><!--Разрушительная Энергия -->
		<ingredient id="35563" count="40"/><!--Сила Гигантов -->
		<ingredient id="19440" count="390"/><!--Самоцвет Ранг R -->
		<ingredient id="17371" count="4685"/><!--Кристалл R -->
	</item>
	<item>
		<production id="35074" count="1"/><!--Темный ПВП диадема айдиоса -->
		<ingredient id="17441" count="1"/><!--Шлем Айдиоса -->
		<ingredient id="35567" count="10"/><!--Усиливающий Камень Темных Доспехов -->
		<ingredient id="35562" count="60"/><!--Разрушительная Энергия -->
		<ingredient id="35563" count="40"/><!--Сила Гигантов -->
		<ingredient id="19440" count="390"/><!--Самоцвет Ранг R -->
		<ingredient id="17371" count="4685"/><!--Кристалл R -->
	</item>
	<item>
		<production id="35063" count="1"/><!--Темный ПВП Шлем Айдиоса -->
		<ingredient id="17430" count="1"/><!--Шлем Айдиоса -->
		<ingredient id="35567" count="10"/><!--Усиливающий Камень Темных Доспехов -->
		<ingredient id="35562" count="48"/><!--Разрушительная Энергия -->
		<ingredient id="35563" count="40"/><!--Сила Гигантов -->
		<ingredient id="19440" count="390"/><!--Самоцвет Ранг R -->
		<ingredient id="17371" count="4685"/><!--Кристалл R -->
		<ingredient id="36515" count="10"/><!--Эльсиум -->
	</item>
	<item>
		<production id="35069" count="1"/><!--Темный ПВП кожанный Шлем Айдиоса -->
		<ingredient id="17436" count="1"/><!--Шлем Айдиоса -->
		<ingredient id="35567" count="10"/><!--Усиливающий Камень Темных Доспехов -->
		<ingredient id="35562" count="48"/><!--Разрушительная Энергия -->
		<ingredient id="35563" count="40"/><!--Сила Гигантов -->
		<ingredient id="19440" count="390"/><!--Самоцвет Ранг R -->
		<ingredient id="17371" count="4685"/><!--Кристалл R -->
		<ingredient id="36515" count="10"/><!--Эльсиум -->
	</item>
	<item>
		<production id="35074" count="1"/><!--Темный ПВП диадема айдиоса -->
		<ingredient id="17441" count="1"/><!--Шлем Айдиоса -->
		<ingredient id="35567" count="10"/><!--Усиливающий Камень Темных Доспехов -->
		<ingredient id="35562" count="48"/><!--Разрушительная Энергия -->
		<ingredient id="35563" count="40"/><!--Сила Гигантов -->
		<ingredient id="19440" count="390"/><!--Самоцвет Ранг R -->
		<ingredient id="17371" count="4685"/><!--Кристалл R -->
		<ingredient id="36515" count="10"/><!--Эльсиум -->
	</item>
	<item>
		<production id="35080" count="1"/><!--Кровавый ПВЕ Кираса Айдиоса -->
		<ingredient id="17431" count="1"/><!--Кираса Айдиоса -->
		<ingredient id="35569" count="20"/><!--Усиливающий Камень Кровавых Доспехов -->
		<ingredient id="35562" count="80"/><!--Разрушительная Энергия -->
		<ingredient id="35563" count="40"/><!--Сила Гигантов -->
		<ingredient id="19440" count="1041"/><!--Самоцвет Ранг R -->
		<ingredient id="17371" count="12494"/><!--Кристалл R -->
	</item>
	<item>
		<production id="35086" count="1"/><!--Кровавый ПВЕ кожанный доспех Айдиоса -->
		<ingredient id="17437" count="1"/><!--кожанный доспех Айдиоса -->
		<ingredient id="35569" count="20"/><!--Усиливающий Камень Кровавых Доспехов -->
		<ingredient id="35562" count="80"/><!--Разрушительная Энергия -->
		<ingredient id="35563" count="40"/><!--Сила Гигантов -->
		<ingredient id="19440" count="1041"/><!--Самоцвет Ранг R -->
		<ingredient id="17371" count="12494"/><!--Кристалл R -->
	</item>
	<item>
		<production id="35091" count="1"/><!--Кровавый ПВЕ туника айдиоса -->
		<ingredient id="17442" count="1"/><!--туника Айдиоса -->
		<ingredient id="35569" count="20"/><!--Усиливающий Камень Кровавых Доспехов -->
		<ingredient id="35562" count="80"/><!--Разрушительная Энергия -->
		<ingredient id="35563" count="40"/><!--Сила Гигантов -->
		<ingredient id="19440" count="1041"/><!--Самоцвет Ранг R -->
		<ingredient id="17371" count="12494"/><!--Кристалл R -->
	</item>
	<item>
		<production id="35080" count="1"/><!--Кровавый ПВЕ Кираса Айдиоса -->
		<ingredient id="17431" count="1"/><!--кираса Айдиоса -->
		<ingredient id="35569" count="20"/><!--Усиливающий Камень Кровавых Доспехов -->
		<ingredient id="35562" count="48"/><!--Разрушительная Энергия -->
		<ingredient id="35563" count="40"/><!--Сила Гигантов -->
		<ingredient id="19440" count="1041"/><!--Самоцвет Ранг R -->
		<ingredient id="17371" count="12494"/><!--Кристалл R -->
		<ingredient id="36515" count="10"/><!--Эльсиум -->
	</item>
	<item>
		<production id="35086" count="1"/><!--Кровавый ПВЕ кожанный Шлем Айдиоса -->
		<ingredient id="17437" count="1"/><!--кожанный доспех Айдиоса -->
		<ingredient id="35569" count="20"/><!--Усиливающий Камень Кровавых Доспехов -->
		<ingredient id="35562" count="48"/><!--Разрушительная Энергия -->
		<ingredient id="35563" count="40"/><!--Сила Гигантов -->
		<ingredient id="19440" count="1041"/><!--Самоцвет Ранг R -->
		<ingredient id="17371" count="12494"/><!--Кристалл R -->
		<ingredient id="36515" count="10"/><!--Эльсиум -->
	</item>
	<item>
		<production id="35091" count="1"/><!--Кровавый ПВЕ туника айдиоса -->
		<ingredient id="17442" count="1"/><!--туника Айдиоса -->
		<ingredient id="35569" count="20"/><!--Усиливающий Камень Кровавых Доспехов -->
		<ingredient id="35562" count="48"/><!--Разрушительная Энергия -->
		<ingredient id="35563" count="40"/><!--Сила Гигантов -->
		<ingredient id="19440" count="1041"/><!--Самоцвет Ранг R -->
		<ingredient id="17371" count="12494"/><!--Кристалл R -->
		<ingredient id="36515" count="10"/><!--Эльсиум -->
	</item>
	<item>
		<production id="35064" count="1"/><!--темный ПВП Кираса Айдиоса -->
		<ingredient id="17431" count="1"/><!--Кираса Айдиоса -->
		<ingredient id="35567" count="20"/><!--Усиливающий Камень Темных Доспехов -->
		<ingredient id="35562" count="80"/><!--Разрушительная Энергия -->
		<ingredient id="35563" count="40"/><!--Сила Гигантов -->
		<ingredient id="19440" count="1041"/><!--Самоцвет Ранг R -->
		<ingredient id="17371" count="12494"/><!--Кристалл R -->
	</item>
	<item>
		<production id="35070" count="1"/><!--темный ПВП кожанный доспех Айдиоса -->
		<ingredient id="17437" count="1"/><!--кожанный доспех Айдиоса -->
		<ingredient id="35567" count="20"/><!--Усиливающий Камень Темных Доспехов -->
		<ingredient id="35562" count="80"/><!--Разрушительная Энергия -->
		<ingredient id="35563" count="40"/><!--Сила Гигантов -->
		<ingredient id="19440" count="1041"/><!--Самоцвет Ранг R -->
		<ingredient id="17371" count="12494"/><!--Кристалл R -->
	</item>
	<item>
		<production id="35075" count="1"/><!--темный ПВП туника айдиоса -->
		<ingredient id="17442" count="1"/><!--туника Айдиоса -->
		<ingredient id="35567" count="20"/><!--Усиливающий Камень Темных Доспехов -->
		<ingredient id="35562" count="80"/><!--Разрушительная Энергия -->
		<ingredient id="35563" count="40"/><!--Сила Гигантов -->
		<ingredient id="19440" count="1041"/><!--Самоцвет Ранг R -->
		<ingredient id="17371" count="12494"/><!--Кристалл R -->
	</item>
	
	
	<item>
		<production id="35064" count="1"/><!--темный ПВП Кираса Айдиоса -->
		<ingredient id="17431" count="1"/><!--кираса Айдиоса -->
		<ingredient id="35567" count="20"/><!--Усиливающий Камень Темных Доспехов -->
		<ingredient id="35562" count="48"/><!--Разрушительная Энергия -->
		<ingredient id="35563" count="40"/><!--Сила Гигантов -->
		<ingredient id="19440" count="1041"/><!--Самоцвет Ранг R -->
		<ingredient id="17371" count="12494"/><!--Кристалл R -->
		<ingredient id="36515" count="10"/><!--Эльсиум -->
	</item>
	<item>
		<production id="35070" count="1"/><!--темный ПВП кожанный Шлем Айдиоса -->
		<ingredient id="17437" count="1"/><!--кожанный доспех Айдиоса -->
		<ingredient id="35567" count="20"/><!--Усиливающий Камень Темных Доспехов -->
		<ingredient id="35562" count="48"/><!--Разрушительная Энергия -->
		<ingredient id="35563" count="40"/><!--Сила Гигантов -->
		<ingredient id="19440" count="1041"/><!--Самоцвет Ранг R -->
		<ingredient id="17371" count="12494"/><!--Кристалл R -->
		<ingredient id="36515" count="10"/><!--Эльсиум -->
	</item>
	<item>
		<production id="35075" count="1"/><!--темный ПВП туника айдиоса -->
		<ingredient id="17442" count="1"/><!--туника Айдиоса -->
		<ingredient id="35567" count="20"/><!--Усиливающий Камень Темных Доспехов -->
		<ingredient id="35562" count="48"/><!--Разрушительная Энергия -->
		<ingredient id="35563" count="40"/><!--Сила Гигантов -->
		<ingredient id="19440" count="1041"/><!--Самоцвет Ранг R -->
		<ingredient id="17371" count="12494"/><!--Кристалл R -->
		<ingredient id="36515" count="10"/><!--Эльсиум -->
	</item>
	<item>
		<production id="35081" count="1"/><!--Кровавый ПВЕ Набедренники Айдиоса -->
		<ingredient id="17432" count="1"/><!--Набедренники Айдиоса -->
		<ingredient id="35569" count="17"/><!--Усиливающий Камень Кровавых Доспехов -->
		<ingredient id="35562" count="80"/><!--Разрушительная Энергия -->
		<ingredient id="35563" count="40"/><!--Сила Гигантов -->
		<ingredient id="19440" count="651"/><!--Самоцвет Ранг R -->
		<ingredient id="17371" count="7809"/><!--Кристалл R -->
	</item>
	<item>
		<production id="35087" count="1"/><!--Кровавый ПВЕ кожанный брюки Айдиоса -->
		<ingredient id="17438" count="1"/><!--кожанный брюки Айдиоса -->
		<ingredient id="35569" count="17"/><!--Усиливающий Камень Кровавых Доспехов -->
		<ingredient id="35562" count="80"/><!--Разрушительная Энергия -->
		<ingredient id="35563" count="40"/><!--Сила Гигантов -->
		<ingredient id="19440" count="651"/><!--Самоцвет Ранг R -->
		<ingredient id="17371" count="7809"/><!--Кристалл R -->
	</item>
	<item>
		<production id="35092" count="1"/><!--Кровавый ПВЕ штаны айдиоса -->
		<ingredient id="17443" count="1"/><!--штаны Айдиоса -->
		<ingredient id="35569" count="17"/><!--Усиливающий Камень Кровавых Доспехов -->
		<ingredient id="35562" count="80"/><!--Разрушительная Энергия -->
		<ingredient id="35563" count="40"/><!--Сила Гигантов -->
		<ingredient id="19440" count="651"/><!--Самоцвет Ранг R -->
		<ingredient id="17371" count="7809"/><!--Кристалл R -->
	</item>
	<item>
		<production id="35081" count="1"/><!--Кровавый ПВЕ Набедренники Айдиоса -->
		<ingredient id="17432" count="1"/><!--Набедренники Айдиоса -->
		<ingredient id="35569" count="17"/><!--Усиливающий Камень Кровавых Доспехов -->
		<ingredient id="35562" count="48"/><!--Разрушительная Энергия -->
		<ingredient id="35563" count="40"/><!--Сила Гигантов -->
		<ingredient id="19440" count="651"/><!--Самоцвет Ранг R -->
		<ingredient id="17371" count="7809"/><!--Кристалл R -->
		<ingredient id="36515" count="10"/><!--Эльсиум -->
	</item>
	<item>
		<production id="35087" count="1"/><!--Кровавый ПВЕ кожанный брюки Айдиоса -->
		<ingredient id="17438" count="1"/><!--кожанный брюки Айдиоса -->
		<ingredient id="35569" count="17"/><!--Усиливающий Камень Кровавых Доспехов -->
		<ingredient id="35562" count="48"/><!--Разрушительная Энергия -->
		<ingredient id="35563" count="40"/><!--Сила Гигантов -->
		<ingredient id="19440" count="651"/><!--Самоцвет Ранг R -->
		<ingredient id="17371" count="7809"/><!--Кристалл R -->
		<ingredient id="36515" count="10"/><!--Эльсиум -->
	</item>
	<item>
		<production id="35092" count="1"/><!--Кровавый ПВЕ штаны айдиоса -->
		<ingredient id="17443" count="1"/><!--штаны Айдиоса -->
		<ingredient id="35569" count="17"/><!--Усиливающий Камень Кровавых Доспехов -->
		<ingredient id="35562" count="48"/><!--Разрушительная Энергия -->
		<ingredient id="35563" count="40"/><!--Сила Гигантов -->
		<ingredient id="19440" count="651"/><!--Самоцвет Ранг R -->
		<ingredient id="17371" count="7809"/><!--Кристалл R -->
		<ingredient id="36515" count="10"/><!--Эльсиум -->
	</item>
	<item>
		<production id="35065" count="1"/><!--Темный ПВП Набедренники Айдиоса -->
		<ingredient id="17432" count="1"/><!--Набедренники Айдиоса -->
		<ingredient id="35567" count="17"/><!--Усиливающий Камень Темных Доспехов -->
		<ingredient id="35562" count="80"/><!--Разрушительная Энергия -->
		<ingredient id="35563" count="40"/><!--Сила Гигантов -->
		<ingredient id="19440" count="651"/><!--Самоцвет Ранг R -->
		<ingredient id="17371" count="7809"/><!--Кристалл R -->
	</item>
	<item>
		<production id="35071" count="1"/><!--Темный ПВП кожанный брюки Айдиоса -->
		<ingredient id="17438" count="1"/><!--кожанный брюки Айдиоса -->
		<ingredient id="35567" count="17"/><!--Усиливающий Камень Темных Доспехов -->
		<ingredient id="35562" count="80"/><!--Разрушительная Энергия -->
		<ingredient id="35563" count="40"/><!--Сила Гигантов -->
		<ingredient id="19440" count="651"/><!--Самоцвет Ранг R -->
		<ingredient id="17371" count="7809"/><!--Кристалл R -->
	</item>
	<item>
		<production id="35076" count="1"/><!--Темный ПВП штаны айдиоса -->
		<ingredient id="17443" count="1"/><!--штаны Айдиоса -->
		<ingredient id="35567" count="17"/><!--Усиливающий Камень Темных Доспехов -->
		<ingredient id="35562" count="80"/><!--Разрушительная Энергия -->
		<ingredient id="35563" count="40"/><!--Сила Гигантов -->
		<ingredient id="19440" count="651"/><!--Самоцвет Ранг R -->
		<ingredient id="17371" count="7809"/><!--Кристалл R -->
	</item>
	<item>
		<production id="35065" count="1"/><!--Темный ПВП Набедренники Айдиоса -->
		<ingredient id="17432" count="1"/><!--Набедренники Айдиоса -->
		<ingredient id="35567" count="17"/><!--Усиливающий Камень Темных Доспехов -->
		<ingredient id="35562" count="48"/><!--Разрушительная Энергия -->
		<ingredient id="35563" count="40"/><!--Сила Гигантов -->
		<ingredient id="19440" count="651"/><!--Самоцвет Ранг R -->
		<ingredient id="17371" count="7809"/><!--Кристалл R -->
		<ingredient id="36515" count="10"/><!--Эльсиум -->
	</item>
	<item>
		<production id="35071" count="1"/><!--Темный ПВП кожанный брюки Айдиоса -->
		<ingredient id="17438" count="1"/><!--кожанный брюки Айдиоса -->
		<ingredient id="35567" count="17"/><!--Усиливающий Камень Темных Доспехов -->
		<ingredient id="35562" count="48"/><!--Разрушительная Энергия -->
		<ingredient id="35563" count="40"/><!--Сила Гигантов -->
		<ingredient id="19440" count="651"/><!--Самоцвет Ранг R -->
		<ingredient id="17371" count="7809"/><!--Кристалл R -->
		<ingredient id="36515" count="10"/><!--Эльсиум -->
	</item>
	<item>
		<production id="35076" count="1"/><!--Темный ПВП штаны айдиоса -->
		<ingredient id="17443" count="1"/><!--штаны Айдиоса -->
		<ingredient id="35567" count="17"/><!--Усиливающий Камень Темных Доспехов -->
		<ingredient id="35562" count="48"/><!--Разрушительная Энергия -->
		<ingredient id="35563" count="40"/><!--Сила Гигантов -->
		<ingredient id="19440" count="651"/><!--Самоцвет Ранг R -->
		<ingredient id="17371" count="7809"/><!--Кристалл R -->
		<ingredient id="36515" count="10"/><!--Эльсиум -->
	</item>
	<item>
		<production id="35082" count="1"/><!--Кровавый ПВЕ рукавицы Айдиоса -->
		<ingredient id="17433" count="1"/><!--рукавицы Айдиоса -->
		<ingredient id="35569" count="8"/><!--Усиливающий Камень Кровавых Доспехов -->
		<ingredient id="35562" count="60"/><!--Разрушительная Энергия -->
		<ingredient id="35563" count="40"/><!--Сила Гигантов -->
		<ingredient id="19440" count="260"/><!--Самоцвет Ранг R -->
		<ingredient id="17371" count="3123"/><!--Кристалл R -->
	</item>
	<item>
		<production id="35088" count="1"/><!--Кровавый ПВЕ кожанный перчатки Айдиоса -->
		<ingredient id="17439" count="1"/><!--кожанный перчатки Айдиоса -->
		<ingredient id="35569" count="8"/><!--Усиливающий Камень Кровавых Доспехов -->
		<ingredient id="35562" count="60"/><!--Разрушительная Энергия -->
		<ingredient id="35563" count="40"/><!--Сила Гигантов -->
		<ingredient id="19440" count="260"/><!--Самоцвет Ранг R -->
		<ingredient id="17371" count="3123"/><!--Кристалл R -->
	</item>
	<item>
		<production id="35093" count="1"/><!--Кровавый ПВЕ перчатки айдиоса -->
		<ingredient id="17444" count="1"/><!--перчатки Айдиоса -->
		<ingredient id="35569" count="8"/><!--Усиливающий Камень Кровавых Доспехов -->
		<ingredient id="35562" count="60"/><!--Разрушительная Энергия -->
		<ingredient id="35563" count="40"/><!--Сила Гигантов -->
		<ingredient id="19440" count="260"/><!--Самоцвет Ранг R -->
		<ingredient id="17371" count="3123"/><!--Кристалл R -->
	</item>
	<item>
		<production id="35082" count="1"/><!--Кровавый ПВЕ рукавицы Айдиоса -->
		<ingredient id="17433" count="1"/><!--рукавицы Айдиоса -->
		<ingredient id="35569" count="8"/><!--Усиливающий Камень Кровавых Доспехов -->
		<ingredient id="35562" count="48"/><!--Разрушительная Энергия -->
		<ingredient id="35563" count="40"/><!--Сила Гигантов -->
		<ingredient id="19440" count="260"/><!--Самоцвет Ранг R -->
		<ingredient id="17371" count="3123"/><!--Кристалл R -->
		<ingredient id="36515" count="10"/><!--Эльсиум -->
	</item>
	<item>
		<production id="35088" count="1"/><!--Кровавый ПВЕ кожанный перчатки Айдиоса -->
		<ingredient id="17439" count="1"/><!--кожанный перчатки Айдиоса -->
		<ingredient id="35569" count="8"/><!--Усиливающий Камень Кровавых Доспехов -->
		<ingredient id="35562" count="48"/><!--Разрушительная Энергия -->
		<ingredient id="35563" count="40"/><!--Сила Гигантов -->
		<ingredient id="19440" count="260"/><!--Самоцвет Ранг R -->
		<ingredient id="17371" count="3123"/><!--Кристалл R -->
		<ingredient id="36515" count="10"/><!--Эльсиум -->
	</item>
	<item>
		<production id="35093" count="1"/><!--Кровавый ПВЕ перчатки айдиоса -->
		<ingredient id="17444" count="1"/><!--перчатки Айдиоса -->
		<ingredient id="35569" count="8"/><!--Усиливающий Камень Кровавых Доспехов -->
		<ingredient id="35562" count="48"/><!--Разрушительная Энергия -->
		<ingredient id="35563" count="40"/><!--Сила Гигантов -->
		<ingredient id="19440" count="260"/><!--Самоцвет Ранг R -->
		<ingredient id="17371" count="3123"/><!--Кристалл R -->
		<ingredient id="36515" count="10"/><!--Эльсиум -->
	</item>
	<item>
		<production id="35066" count="1"/><!--Темный ПВП рукавицы Айдиоса -->
		<ingredient id="17433" count="1"/><!--рукавицы Айдиоса -->
		<ingredient id="35567" count="8"/><!--Усиливающий Камень Темных Доспехов -->
		<ingredient id="35562" count="60"/><!--Разрушительная Энергия -->
		<ingredient id="35563" count="40"/><!--Сила Гигантов -->
		<ingredient id="19440" count="260"/><!--Самоцвет Ранг R -->
		<ingredient id="17371" count="3123"/><!--Кристалл R -->
	</item>
	<item>
		<production id="35072" count="1"/><!--Темный ПВП кожанный перчатки Айдиоса -->
		<ingredient id="17439" count="1"/><!--кожанный перчатки Айдиоса -->
		<ingredient id="35567" count="8"/><!--Усиливающий Камень Темных Доспехов -->
		<ingredient id="35562" count="60"/><!--Разрушительная Энергия -->
		<ingredient id="35563" count="40"/><!--Сила Гигантов -->
		<ingredient id="19440" count="260"/><!--Самоцвет Ранг R -->
		<ingredient id="17371" count="3123"/><!--Кристалл R -->
	</item>
	<item>
		<production id="35077" count="1"/><!--Темный ПВП перчатки айдиоса -->
		<ingredient id="17444" count="1"/><!--перчатки Айдиоса -->
		<ingredient id="35567" count="8"/><!--Усиливающий Камень Темных Доспехов -->
		<ingredient id="35562" count="60"/><!--Разрушительная Энергия -->
		<ingredient id="35563" count="40"/><!--Сила Гигантов -->
		<ingredient id="19440" count="260"/><!--Самоцвет Ранг R -->
		<ingredient id="17371" count="3123"/><!--Кристалл R -->
	</item>
	<item>
		<production id="35066" count="1"/><!--Темный ПВП рукавицы Айдиоса -->
		<ingredient id="17433" count="1"/><!--рукавицы Айдиоса -->
		<ingredient id="35567" count="8"/><!--Усиливающий Камень Темных Доспехов -->
		<ingredient id="35562" count="48"/><!--Разрушительная Энергия -->
		<ingredient id="35563" count="40"/><!--Сила Гигантов -->
		<ingredient id="19440" count="260"/><!--Самоцвет Ранг R -->
		<ingredient id="17371" count="3123"/><!--Кристалл R -->
		<ingredient id="36515" count="10"/><!--Эльсиум -->
	</item>
	<item>
		<production id="35072" count="1"/><!--Темный ПВП кожанный перчатки Айдиоса -->
		<ingredient id="17439" count="1"/><!--кожанный перчатки Айдиоса -->
		<ingredient id="35567" count="8"/><!--Усиливающий Камень Темных Доспехов -->
		<ingredient id="35562" count="48"/><!--Разрушительная Энергия -->
		<ingredient id="35563" count="40"/><!--Сила Гигантов -->
		<ingredient id="19440" count="260"/><!--Самоцвет Ранг R -->
		<ingredient id="17371" count="3123"/><!--Кристалл R -->
		<ingredient id="36515" count="10"/><!--Эльсиум -->
	</item>
	<item>
		<production id="35077" count="1"/><!--Темный ПВП перчатки айдиоса -->
		<ingredient id="17444" count="1"/><!--перчатки Айдиоса -->
		<ingredient id="35567" count="8"/><!--Усиливающий Камень Темных Доспехов -->
		<ingredient id="35562" count="48"/><!--Разрушительная Энергия -->
		<ingredient id="35563" count="40"/><!--Сила Гигантов -->
		<ingredient id="19440" count="260"/><!--Самоцвет Ранг R -->
		<ingredient id="17371" count="3123"/><!--Кристалл R -->
		<ingredient id="36515" count="10"/><!--Эльсиум -->
	</item>
	<item>
		<production id="35083" count="1"/><!--Кровавый ПВЕ сапоги Айдиоса -->
		<ingredient id="17434" count="1"/><!--сапоги Айдиоса -->
		<ingredient id="35569" count="8"/><!--Усиливающий Камень Кровавых Доспехов -->
		<ingredient id="35562" count="60"/><!--Разрушительная Энергия -->
		<ingredient id="35563" count="40"/><!--Сила Гигантов -->
		<ingredient id="19440" count="260"/><!--Самоцвет Ранг R -->
		<ingredient id="17371" count="3123"/><!--Кристалл R -->
	</item>
	<item>
		<production id="35089" count="1"/><!--Кровавый ПВЕ кожаные сапоги  Айдиоса -->
		<ingredient id="17440" count="1"/><!-- кожаные сапоги  Айдиоса -->
		<ingredient id="35569" count="8"/><!--Усиливающий Камень Кровавых Доспехов -->
		<ingredient id="35562" count="60"/><!--Разрушительная Энергия -->
		<ingredient id="35563" count="40"/><!--Сила Гигантов -->
		<ingredient id="19440" count="260"/><!--Самоцвет Ранг R -->
		<ingredient id="17371" count="3123"/><!--Кристалл R -->
	</item>
	<item>
		<production id="35094" count="1"/><!--Кровавый ПВЕ ботинки айдиоса -->
		<ingredient id="17445" count="1"/><!--ботинки Айдиоса -->
		<ingredient id="35569" count="8"/><!--Усиливающий Камень Кровавых Доспехов -->
		<ingredient id="35562" count="60"/><!--Разрушительная Энергия -->
		<ingredient id="35563" count="40"/><!--Сила Гигантов -->
		<ingredient id="19440" count="260"/><!--Самоцвет Ранг R -->
		<ingredient id="17371" count="3123"/><!--Кристалл R -->
	</item>
	<item>
		<production id="35083" count="1"/><!--Кровавый ПВЕ сапоги Айдиоса -->
		<ingredient id="17434" count="1"/><!--сапоги Айдиоса -->
		<ingredient id="35569" count="8"/><!--Усиливающий Камень Кровавых Доспехов -->
		<ingredient id="35562" count="48"/><!--Разрушительная Энергия -->
		<ingredient id="35563" count="40"/><!--Сила Гигантов -->
		<ingredient id="19440" count="260"/><!--Самоцвет Ранг R -->
		<ingredient id="17371" count="3123"/><!--Кристалл R -->
		<ingredient id="36515" count="10"/><!--Эльсиум -->
	</item>
	<item>
		<production id="35089" count="1"/><!--Кровавый ПВЕ  кожаные сапоги  Айдиоса -->
		<ingredient id="17440" count="1"/><!-- кожаные сапоги  Айдиоса -->
		<ingredient id="35569" count="8"/><!--Усиливающий Камень Кровавых Доспехов -->
		<ingredient id="35562" count="48"/><!--Разрушительная Энергия -->
		<ingredient id="35563" count="40"/><!--Сила Гигантов -->
		<ingredient id="19440" count="260"/><!--Самоцвет Ранг R -->
		<ingredient id="17371" count="3123"/><!--Кристалл R -->
		<ingredient id="36515" count="10"/><!--Эльсиум -->
	</item>
	<item>
		<production id="35094" count="1"/><!--Кровавый ПВЕ ботинки айдиоса -->
		<ingredient id="17445" count="1"/><!--ботинки Айдиоса -->
		<ingredient id="35569" count="8"/><!--Усиливающий Камень Кровавых Доспехов -->
		<ingredient id="35562" count="48"/><!--Разрушительная Энергия -->
		<ingredient id="35563" count="40"/><!--Сила Гигантов -->
		<ingredient id="19440" count="260"/><!--Самоцвет Ранг R -->
		<ingredient id="17371" count="3123"/><!--Кристалл R -->
		<ingredient id="36515" count="10"/><!--Эльсиум -->
	</item>
		<item>
		<production id="35067" count="1"/><!--Темный ПВП сапоги Айдиоса -->
		<ingredient id="17434" count="1"/><!--сапоги Айдиоса -->
		<ingredient id="35567" count="8"/><!--Усиливающий Камень Темных Доспехов -->
		<ingredient id="35562" count="60"/><!--Разрушительная Энергия -->
		<ingredient id="35563" count="40"/><!--Сила Гигантов -->
		<ingredient id="19440" count="260"/><!--Самоцвет Ранг R -->
		<ingredient id="17371" count="3123"/><!--Кристалл R -->
	</item>
	<item>
		<production id="35073" count="1"/><!--Темный ПВП кожанный сапоги Айдиоса -->
		<ingredient id="17440" count="1"/><!--кожанный сапоги Айдиоса -->
		<ingredient id="35567" count="8"/><!--Усиливающий Камень Темных Доспехов -->
		<ingredient id="35562" count="60"/><!--Разрушительная Энергия -->
		<ingredient id="35563" count="40"/><!--Сила Гигантов -->
		<ingredient id="19440" count="260"/><!--Самоцвет Ранг R -->
		<ingredient id="17371" count="3123"/><!--Кристалл R -->
	</item>
	<item>
		<production id="35078" count="1"/><!--Темный ПВП сапоги айдиоса -->
		<ingredient id="17445" count="1"/><!--сапоги Айдиоса -->
		<ingredient id="35567" count="8"/><!--Усиливающий Камень Темных Доспехов -->
		<ingredient id="35562" count="60"/><!--Разрушительная Энергия -->
		<ingredient id="35563" count="40"/><!--Сила Гигантов -->
		<ingredient id="19440" count="260"/><!--Самоцвет Ранг R -->
		<ingredient id="17371" count="3123"/><!--Кристалл R -->
	</item>
	
	
	<item>
		<production id="35067" count="1"/><!--Темный ПВП сапоги Айдиоса -->
		<ingredient id="17434" count="1"/><!--сапоги Айдиоса -->
		<ingredient id="35567" count="8"/><!--Усиливающий Камень Темных Доспехов -->
		<ingredient id="35562" count="48"/><!--Разрушительная Энергия -->
		<ingredient id="35563" count="40"/><!--Сила Гигантов -->
		<ingredient id="19440" count="260"/><!--Самоцвет Ранг R -->
		<ingredient id="17371" count="3123"/><!--Кристалл R -->
		<ingredient id="36515" count="10"/><!--Эльсиум -->
	</item>
	<item>
		<production id="35073" count="1"/><!--Темный ПВП кожанный сапоги Айдиоса -->
		<ingredient id="17440" count="1"/><!--кожанный сапоги Айдиоса -->
		<ingredient id="35567" count="8"/><!--Усиливающий Камень Темных Доспехов -->
		<ingredient id="35562" count="48"/><!--Разрушительная Энергия -->
		<ingredient id="35563" count="40"/><!--Сила Гигантов -->
		<ingredient id="19440" count="260"/><!--Самоцвет Ранг R -->
		<ingredient id="17371" count="3123"/><!--Кристалл R -->
		<ingredient id="36515" count="10"/><!--Эльсиум -->
	</item>
	<item>
		<production id="35078" count="1"/><!--Темный ПВП сапоги айдиоса -->
		<ingredient id="17445" count="1"/><!--сапоги Айдиоса -->
		<ingredient id="35567" count="8"/><!--Усиливающий Камень Темных Доспехов -->
		<ingredient id="35562" count="48"/><!--Разрушительная Энергия -->
		<ingredient id="35563" count="40"/><!--Сила Гигантов -->
		<ingredient id="19440" count="260"/><!--Самоцвет Ранг R -->
		<ingredient id="17371" count="3123"/><!--Кристалл R -->
		<ingredient id="36515" count="10"/><!--Эльсиум -->
	</item>
</list>