<?xml version="1.0" encoding="UTF-8"?>
<!DOCTYPE list SYSTEM "option_data.dtd">
<list>
	<option_data id="28900">
		<!--M. Def. +35.56-->
	</option_data>
	<option_data id="28901">
		<!--Max HP +67.88-->
	</option_data>
	<option_data id="28902">
		<!--Max MP +76.78-->
	</option_data>
	<option_data id="28903">
		<!--Max CP +110.71-->
	</option_data>
	<option_data id="28904">
		<!--P. Atk. +43.86-->
	</option_data>
	<option_data id="28905">
		<!--M. Atk. +55.19-->
	</option_data>
	<option_data id="28906">
		<!--HP Recovery +0.29-->
	</option_data>
	<option_data id="28907">
		<!--MP Recovery +0.19-->
	</option_data>
	<option_data id="28908">
		<!--CP Recovery +0.29-->
	</option_data>
	<option_data id="28909">
		<!--Evasion +2.351-->
	</option_data>
	<option_data id="28910">
		<!--Accuracy +3.408-->
	</option_data>
	<option_data id="28911">
		<!--Critical +25.5-->
	</option_data>
	<option_data id="28912">
		<!--P. Def. +19.645-->
		<!--M. Def. +17.78-->
	</option_data>
	<option_data id="28913">
		<!--P. Def. +19.645-->
		<!--Max HP +33.94-->
	</option_data>
	<option_data id="28914">
		<!--P. Def. +19.645-->
		<!--Max MP +38.39-->
	</option_data>
	<option_data id="28915">
		<!--P. Def. +19.645-->
		<!--Max CP +55.35-->
	</option_data>
	<option_data id="28916">
		<!--P. Def. +19.645-->
		<!--P. Atk. +21.93-->
	</option_data>
	<option_data id="28917">
		<!--P. Def. +19.645-->
		<!--M. Atk. +27.595-->
	</option_data>
	<option_data id="28918">
		<!--P. Def. +19.645-->
		<!--HP Recovery +0.145-->
	</option_data>
	<option_data id="28919">
		<!--P. Def. +19.645-->
		<!--MP Recovery +0.095-->
	</option_data>
	<option_data id="28920">
		<!--P. Def. +19.645-->
		<!--CP Recovery +0.145-->
	</option_data>
	<option_data id="28921">
		<!--P. Def. +19.645-->
		<!--Evasion +1.1755-->
	</option_data>
	<option_data id="28922">
		<!--P. Def. +19.645-->
		<!--Accuracy +1.704-->
	</option_data>
	<option_data id="28923">
		<!--P. Def. +19.645-->
		<!--Critical +12.75-->
	</option_data>
	<option_data id="28924">
		<!--M. Def. +17.78-->
		<!--Max HP +33.94-->
	</option_data>
	<option_data id="28925">
		<!--M. Def. +17.78-->
		<!--Max MP +38.39-->
	</option_data>
	<option_data id="28926">
		<!--M. Def. +17.78-->
		<!--Max CP +55.35-->
	</option_data>
	<option_data id="28927">
		<!--M. Def. +17.78-->
		<!--P. Atk. +21.93-->
	</option_data>
	<option_data id="28928">
		<!--M. Def. +17.78-->
		<!--M. Atk. +27.595-->
	</option_data>
	<option_data id="28929">
		<!--M. Def. +17.78-->
		<!--HP Recovery +0.145-->
	</option_data>
	<option_data id="28930">
		<!--M. Def. +17.78-->
		<!--MP Recovery +0.095-->
	</option_data>
	<option_data id="28931">
		<!--M. Def. +17.78-->
		<!--CP Recovery +0.145-->
	</option_data>
	<option_data id="28932">
		<!--M. Def. +17.78-->
		<!--Evasion +1.1755-->
	</option_data>
	<option_data id="28933">
		<!--M. Def. +17.78-->
		<!--Accuracy +1.704-->
	</option_data>
	<option_data id="28934">
		<!--M. Def. +17.78-->
		<!--Critical +12.75-->
	</option_data>
	<option_data id="28935">
		<!--Max HP +33.94-->
		<!--Max MP +38.39-->
	</option_data>
	<option_data id="28936">
		<!--Max HP +33.94-->
		<!--Max CP +55.35-->
	</option_data>
	<option_data id="28937">
		<!--Max HP +33.94-->
		<!--P. Atk. +21.93-->
	</option_data>
	<option_data id="28938">
		<!--Max HP +33.94-->
		<!--M. Atk. +27.595-->
	</option_data>
	<option_data id="28939">
		<!--Max HP +33.94-->
		<!--HP Recovery +0.145-->
	</option_data>
	<option_data id="28940">
		<!--Max HP +33.94-->
		<!--MP Recovery +0.095-->
	</option_data>
	<option_data id="28941">
		<!--Max HP +33.94-->
		<!--CP Recovery +0.145-->
	</option_data>
	<option_data id="28942">
		<!--Max HP +33.94-->
		<!--Evasion +1.1755-->
	</option_data>
	<option_data id="28943">
		<!--Max HP +33.94-->
		<!--Accuracy +1.704-->
	</option_data>
	<option_data id="28944">
		<!--Max HP +33.94-->
		<!--Critical +12.75-->
	</option_data>
	<option_data id="28945">
		<!--Max MP +38.39-->
		<!--Max CP +55.35-->
	</option_data>
	<option_data id="28946">
		<!--Max MP +38.39-->
		<!--P. Atk. +21.93-->
	</option_data>
	<option_data id="28947">
		<!--Max MP +38.39-->
		<!--M. Atk. +27.595-->
	</option_data>
	<option_data id="28948">
		<!--Max MP +38.39-->
		<!--HP Recovery +0.145-->
	</option_data>
	<option_data id="28949">
		<!--Max MP +38.39-->
		<!--MP Recovery +0.095-->
	</option_data>
	<option_data id="28950">
		<!--Max MP +38.39-->
		<!--CP Recovery +0.145-->
	</option_data>
	<option_data id="28951">
		<!--Max MP +38.39-->
		<!--Evasion +1.1755-->
	</option_data>
	<option_data id="28952">
		<!--Max MP +38.39-->
		<!--Accuracy +1.704-->
	</option_data>
	<option_data id="28953">
		<!--Max MP +38.39-->
		<!--Critical +12.75-->
	</option_data>
	<option_data id="28954">
		<!--Max CP +55.35-->
		<!--P. Atk. +21.93-->
	</option_data>
	<option_data id="28955">
		<!--Max CP +55.35-->
		<!--M. Atk. +27.595-->
	</option_data>
	<option_data id="28956">
		<!--Max CP +55.35-->
		<!--HP Recovery +0.145-->
	</option_data>
	<option_data id="28957">
		<!--Max CP +55.35-->
		<!--MP Recovery +0.095-->
	</option_data>
	<option_data id="28958">
		<!--Max CP +55.35-->
		<!--CP Recovery +0.145-->
	</option_data>
	<option_data id="28959">
		<!--Max CP +55.35-->
		<!--Evasion +1.1755-->
	</option_data>
	<option_data id="28960">
		<!--Max CP +55.35-->
		<!--Accuracy +1.704-->
	</option_data>
	<option_data id="28961">
		<!--Max CP +55.35-->
		<!--Critical +12.75-->
	</option_data>
	<option_data id="28962">
		<!--P. Atk. +21.93-->
		<!--M. Atk. +27.595-->
	</option_data>
	<option_data id="28963">
		<!--P. Atk. +21.93-->
		<!--HP Recovery +0.145-->
	</option_data>
	<option_data id="28964">
		<!--P. Atk. +21.93-->
		<!--MP Recovery +0.095-->
	</option_data>
	<option_data id="28965">
		<!--P. Atk. +21.93-->
		<!--CP Recovery +0.145-->
	</option_data>
	<option_data id="28966">
		<!--P. Atk. +21.93-->
		<!--Evasion +1.1755-->
	</option_data>
	<option_data id="28967">
		<!--P. Atk. +21.93-->
		<!--Accuracy +1.704-->
	</option_data>
	<option_data id="28968">
		<!--P. Atk. +21.93-->
		<!--Critical +12.75-->
	</option_data>
	<option_data id="28969">
		<!--M. Atk. +27.595-->
		<!--HP Recovery +0.145-->
	</option_data>
	<option_data id="28970">
		<!--M. Atk. +27.595-->
		<!--MP Recovery +0.095-->
	</option_data>
	<option_data id="28971">
		<!--M. Atk. +27.595-->
		<!--CP Recovery +0.145-->
	</option_data>
	<option_data id="28972">
		<!--M. Atk. +27.595-->
		<!--Evasion +1.1755-->
	</option_data>
	<option_data id="28973">
		<!--M. Atk. +27.595-->
		<!--Accuracy +1.704-->
	</option_data>
	<option_data id="28974">
		<!--M. Atk. +27.595-->
		<!--Critical +12.75-->
	</option_data>
	<option_data id="28975">
		<!--HP Recovery +0.145-->
		<!--MP Recovery +0.095-->
	</option_data>
	<option_data id="28976">
		<!--HP Recovery +0.145-->
		<!--CP Recovery +0.145-->
	</option_data>
	<option_data id="28977">
		<!--HP Recovery +0.145-->
		<!--Evasion +1.1755-->
	</option_data>
	<option_data id="28978">
		<!--HP Recovery +0.145-->
		<!--Accuracy +1.704-->
	</option_data>
	<option_data id="28979">
		<!--HP Recovery +0.145-->
		<!--Critical +12.75-->
	</option_data>
	<option_data id="28980">
		<!--MP Recovery +0.095-->
		<!--CP Recovery +0.145-->
	</option_data>
	<option_data id="28981">
		<!--MP Recovery +0.095-->
		<!--Evasion +1.1755-->
	</option_data>
	<option_data id="28982">
		<!--MP Recovery +0.095-->
		<!--Accuracy +1.704-->
	</option_data>
	<option_data id="28983">
		<!--MP Recovery +0.095-->
		<!--Critical +12.75-->
	</option_data>
	<option_data id="28984">
		<!--CP Recovery +0.145-->
		<!--Evasion +1.1755-->
	</option_data>
	<option_data id="28985">
		<!--CP Recovery +0.145-->
		<!--Accuracy +1.704-->
	</option_data>
	<option_data id="28986">
		<!--CP Recovery +0.145-->
		<!--Critical +12.75-->
	</option_data>
	<option_data id="28987">
		<!--Evasion +1.1755-->
		<!--Accuracy +1.704-->
	</option_data>
	<option_data id="28988">
		<!--Evasion +1.1755-->
		<!--Critical +12.75-->
	</option_data>
	<option_data id="28989">
		<!--Accuracy +1.704-->
		<!--Critical +12.75-->
	</option_data>
	<option_data id="28990">
		<!--P. Def. +43.45-->
	</option_data>
	<option_data id="28991">
		<!--M. Def. +40.11-->
	</option_data>
	<option_data id="28992">
		<!--Max HP +70.58-->
	</option_data>
	<option_data id="28993">
		<!--Max MP +83.37-->
	</option_data>
	<option_data id="28994">
		<!--Max CP +116.24-->
	</option_data>
	<option_data id="28995">
		<!--P. Atk. +52.23-->
	</option_data>
	<option_data id="28996">
		<!--M. Atk. +67.53-->
	</option_data>
	<option_data id="28997">
		<!--HP Recovery +0.3-->
	</option_data>
	<option_data id="28998">
		<!--MP Recovery +0.19-->
	</option_data>
	<option_data id="28999">
		<!--CP Recovery +0.3-->
	</option_data>
</list>