<?xml version="1.0" encoding="UTF-8"?>
<!DOCTYPE list SYSTEM "skill.dtd">
<list>
	<skill id="36318" levels="200" name="Сказания Героя">
		<set name="magicLevel" value="1"/>
		<set name="operate_type" value="P"/>
		<table name="#hpcpmp">1.001 1.002 1.003 1.004 1.005 1.006 1.007 1.008 1.009 1.01 1.011 1.012 1.013 1.014 1.015 1.016 1.017 1.018 1.019 1.02 1.021 1.022 1.023 1.024 1.025 1.026 1.027 1.028 1.029 1.03 1.031 1.032 1.033 1.034 1.035 1.036 1.037 1.038 1.039 1.04 1.041 1.042 1.043 1.044 1.045 1.046 1.047 1.048 1.049 1.05 1.051 1.052 1.053 1.054 1.055 1.056 1.057 1.058 1.059 1.06 1.061 1.062 1.063 1.064 1.065 1.066 1.067 1.068 1.069 1.07 1.071 1.072 1.073 1.074 1.075 1.076 1.077 1.078 1.079 1.08 1.081 1.082 1.083 1.084 1.085 1.086 1.087 1.088 1.089 1.09 1.091 1.092 1.093 1.094 1.095 1.096 1.097 1.098 1.099 1.1 1.101 1.102 1.103 1.104 1.105 1.106 1.107 1.108 1.109 1.11 1.111 1.112 1.113 1.114 1.115 1.116 1.117 1.118 1.119 1.12 1.121 1.122 1.123 1.124 1.125 1.126 1.127 1.128 1.129 1.13 1.131 1.132 1.133 1.134 1.135 1.136 1.137 1.138 1.139 1.14 1.141 1.142 1.143 1.144 1.145 1.146 1.147 1.148 1.149 1.15 1.151 1.152 1.153 1.154 1.155 1.156 1.157 1.158 1.159 1.16 1.161 1.162 1.163 1.164 1.165 1.166 1.167 1.168 1.169 1.17 1.171 1.172 1.173 1.174 1.175 1.176 1.177 1.178 1.179 1.18 1.181 1.182 1.183 1.184 1.185 1.186 1.187 1.188 1.189 1.19 1.191 1.192 1.193 1.194 1.195 1.196 1.197 1.198 1.199 1.2</table>
		<table name="#PMDef">1 1 1 1 1 1 1 1 1 1 1.001 1.002 1.003 1.004 1.005 1.006 1.007 1.008 1.009 1.01 1.011 1.012 1.013 1.014 1.015 1.016 1.017 1.018 1.019 1.02 1.021 1.022 1.023 1.024 1.025 1.026 1.027 1.028 1.029 1.03 1.031 1.032 1.033 1.034 1.035 1.036 1.037 1.038 1.039 1.04 1.041 1.042 1.043 1.044 1.045 1.046 1.047 1.048 1.049 1.05 1.051 1.052 1.053 1.054 1.055 1.056 1.057 1.058 1.059 1.06 1.061 1.062 1.063 1.064 1.065 1.066 1.067 1.068 1.069 1.07 1.071 1.072 1.073 1.074 1.075 1.076 1.077 1.078 1.079 1.08 1.081 1.082 1.083 1.084 1.085 1.086 1.087 1.088 1.089 1.09 1.091 1.092 1.093 1.094 1.095 1.096 1.097 1.098 1.099 1.1 1.101 1.102 1.103 1.104 1.105 1.106 1.107 1.108 1.109 1.11 1.111 1.112 1.113 1.114 1.115 1.116 1.117 1.118 1.119 1.12 1.121 1.122 1.123 1.124 1.125 1.126 1.127 1.128 1.129 1.13 1.131 1.132 1.133 1.134 1.135 1.136 1.137 1.138 1.139 1.14 1.141 1.142 1.143 1.144 1.145 1.146 1.147 1.148 1.149 1.15 1.151 1.152 1.153 1.154 1.155 1.156 1.157 1.158 1.159 1.16 1.161 1.162 1.163 1.164 1.165 1.166 1.167 1.168 1.169 1.17 1.171 1.172 1.173 1.174 1.175 1.176 1.177 1.178 1.179 1.18 1.181 1.182 1.183 1.184 1.185 1.186 1.187 1.188 1.189 1.19</table>
		<table name="#PMCritPower">0 0 0 0 0 0 0 0 0 0 0 0 0 0 0 0 0 0 0 0 0.1 0.2 0.3 0.4 0.5 0.6 0.7 0.8 0.9 1 1.1 1.2 1.3 1.4 1.5 1.6 1.7 1.8 1.9 2 2.1 2.2 2.3 2.4 2.5 2.6 2.7 2.8 2.9 3 3.1 3.2 3.3 3.4 3.5 3.6 3.7 3.8 3.9 4 4.1 4.2 4.3 4.4 4.5 4.6 4.7 4.8 4.9 5 5.1 5.2 5.3 5.4 5.5 5.6 5.7 5.8 5.9 6 6.1 6.2 6.3 6.4 6.5 6.6 6.7 6.8 6.9 7 7.1 7.2 7.3 7.4 7.5 7.6 7.7 7.8 7.9 8 8.1 8.2 8.3 8.4 8.5 8.6 8.7 8.8 8.9 9 9.1 9.2 9.3 9.4 9.5 9.6 9.7 9.8 9.9 10 10.1 10.2 10.3 10.4 10.5 10.6 10.7 10.8 10.9 11 11.1 11.2 11.3 11.4 11.5 11.6 11.7 11.8 11.9 12 12.1 12.2 12.3 12.4 12.5 12.6 12.7 12.8 12.9 13 13.1 13.2 13.3 13.4 13.5 13.6 13.7 13.8 13.9 14 14.1 14.2 14.3 14.4 14.5 14.6 14.7 14.8 14.9 15 15.1 15.2 15.3 15.4 15.5 15.6 15.7 15.8 15.9 16 16.1 16.2 16.3 16.4 16.5 16.6 16.7 16.8 16.9 17 17.1 17.2 17.3 17.4 17.5 17.6 17.7 17.8 17.9 18</table>
		<table name="#PvpDmg">1 1 1 1 1 1 1 1 1 1 1 1 1 1 1 1 1 1 1 1 1 1 1 1 1 1 1 1 1 1 1.002 1.004 1.006 1.008 1.01 1.012 1.014 1.016 1.018 1.02 1.022 1.024 1.026 1.028 1.03 1.032 1.034 1.036 1.038 1.04 1.042 1.044 1.046 1.048 1.05 1.052 1.054 1.056 1.058 1.06 1.062 1.064 1.066 1.068 1.07 1.072 1.074 1.076 1.078 1.08 1.082 1.084 1.086 1.088 1.09 1.092 1.094 1.096 1.098 1.1 1.102 1.104 1.106 1.108 1.11 1.112 1.114 1.116 1.118 1.12 1.122 1.124 1.126 1.128 1.13 1.132 1.134 1.136 1.138 1.14 1.142 1.144 1.146 1.148 1.15 1.152 1.154 1.156 1.158 1.16 1.162 1.164 1.166 1.168 1.17 1.172 1.174 1.176 1.178 1.18 1.182 1.184 1.186 1.188 1.19 1.192 1.194 1.196 1.198 1.2 1.202 1.204 1.206 1.208 1.21 1.212 1.214 1.216 1.218 1.22 1.222 1.224 1.226 1.228 1.23 1.232 1.234 1.236 1.238 1.24 1.242 1.244 1.246 1.248 1.25 1.252 1.254 1.256 1.258 1.26 1.262 1.264 1.266 1.268 1.27 1.272 1.274 1.276 1.278 1.28 1.282 1.284 1.286 1.288 1.29 1.292 1.294 1.296 1.298 1.3 1.302 1.304 1.306 1.308 1.31 1.312 1.314 1.316 1.318 1.32 1.322 1.324 1.326 1.328 1.33 1.332 1.334 1.336 1.338 1.34</table>
		<table name="#PvpDef">1 1 1 1 1 1 1 1 1 1 1 1 1 1 1 1 1 1 1 1 1 1 1 1 1 1 1 1 1 1 1.001 1.002 1.003 1.004 1.005 1.006 1.007 1.008 1.009 1.01 1.011 1.012 1.013 1.014 1.015 1.016 1.017 1.018 1.019 1.02 1.021 1.022 1.023 1.024 1.025 1.026 1.027 1.028 1.029 1.03 1.031 1.032 1.033 1.034 1.035 1.036 1.037 1.038 1.039 1.04 1.041 1.042 1.043 1.044 1.045 1.046 1.047 1.048 1.049 1.05 1.051 1.052 1.053 1.054 1.055 1.056 1.057 1.058 1.059 1.06 1.061 1.062 1.063 1.064 1.065 1.066 1.067 1.068 1.069 1.07 1.071 1.072 1.073 1.074 1.075 1.076 1.077 1.078 1.079 1.08 1.081 1.082 1.083 1.084 1.085 1.086 1.087 1.088 1.089 1.09 1.091 1.092 1.093 1.094 1.095 1.096 1.097 1.098 1.099 1.1 1.101 1.102 1.103 1.104 1.105 1.106 1.107 1.108 1.109 1.11 1.111 1.112 1.113 1.114 1.115 1.116 1.117 1.118 1.119 1.12 1.121 1.122 1.123 1.124 1.125 1.126 1.127 1.128 1.129 1.13 1.131 1.132 1.133 1.134 1.135 1.136 1.137 1.138 1.139 1.14 1.141 1.142 1.143 1.144 1.145 1.146 1.147 1.148 1.149 1.15 1.151 1.152 1.153 1.154 1.155 1.156 1.157 1.158 1.159 1.16 1.161 1.162 1.163 1.164 1.165 1.166 1.167 1.168 1.169 1.170</table>
		<table name="#PveDmg">1 1 1 1 1 1 1 1 1 1 1 1 1 1 1 1 1 1 1 1 1 1 1 1 1 1 1 1 1 1 1 1 1 1 1 1 1 1 1 1 1.002 1.004 1.006 1.008 1.01 1.012 1.014 1.016 1.018 1.02 1.022 1.024 1.026 1.028 1.03 1.032 1.034 1.036 1.038 1.04 1.042 1.044 1.046 1.048 1.05 1.052 1.054 1.056 1.058 1.06 1.062 1.064 1.066 1.068 1.07 1.072 1.074 1.076 1.078 1.08 1.082 1.084 1.086 1.088 1.09 1.092 1.094 1.096 1.098 1.1 1.102 1.104 1.106 1.108 1.11 1.112 1.114 1.116 1.118 1.12 1.122 1.124 1.126 1.128 1.13 1.132 1.134 1.136 1.138 1.14 1.142 1.144 1.146 1.148 1.15 1.152 1.154 1.156 1.158 1.16 1.162 1.164 1.166 1.168 1.17 1.172 1.174 1.176 1.178 1.18 1.182 1.184 1.186 1.188 1.19 1.192 1.194 1.196 1.198 1.2 1.202 1.204 1.206 1.208 1.21 1.212 1.214 1.216 1.218 1.22 1.222 1.224 1.226 1.228 1.23 1.232 1.234 1.236 1.238 1.24 1.242 1.244 1.246 1.248 1.25 1.252 1.254 1.256 1.258 1.26 1.262 1.264 1.266 1.268 1.27 1.272 1.274 1.276 1.278 1.28 1.282 1.284 1.286 1.288 1.29 1.292 1.294 1.296 1.298 1.3 1.302 1.304 1.306 1.308 1.31 1.312 1.314 1.316 1.318 1.32</table>
		<table name="#raid_boss_damage">1 1 1 1 1 1 1 1 1 1 1 1 1 1 1 1 1 1 1 1 1 1 1 1 1 1 1 1 1 1 1 1 1 1 1 1 1 1 1 1 1 1 1 1 1 1 1 1 1 1 1 1 1 1 1 1 1 1 1 1 1.002 1.004 1.006 1.008 1.01 1.012 1.014 1.016 1.018 1.02 1.022 1.024 1.026 1.028 1.03 1.032 1.034 1.036 1.038 1.04 1.042 1.044 1.046 1.048 1.05 1.052 1.054 1.056 1.058 1.06 1.062 1.064 1.066 1.068 1.07 1.072 1.074 1.076 1.078 1.08 1.082 1.084 1.086 1.088 1.09 1.092 1.094 1.096 1.098 1.1 1.102 1.104 1.106 1.108 1.11 1.112 1.114 1.116 1.118 1.12 1.122 1.124 1.126 1.128 1.13 1.132 1.134 1.136 1.138 1.14 1.142 1.144 1.146 1.148 1.15 1.152 1.154 1.156 1.158 1.16 1.162 1.164 1.166 1.168 1.17 1.172 1.174 1.176 1.178 1.18 1.182 1.184 1.186 1.188 1.19 1.192 1.194 1.196 1.198 1.2 1.202 1.204 1.206 1.208 1.21 1.212 1.214 1.216 1.218 1.22 1.222 1.224 1.226 1.228 1.23 1.232 1.234 1.236 1.238 1.24 1.242 1.244 1.246 1.248 1.25 1.252 1.254 1.256 1.258 1.26 1.262 1.264 1.266 1.268 1.27 1.272 1.274 1.276 1.278 1.28</table>
		<for>
			<mul stat="maxHp" value="#hpcpmp"/>
			<mul stat="maxMp" value="#hpcpmp"/>
			<mul stat="maxCp" value="#hpcpmp"/>
			<mul stat="pDef" value="#PMDef"/>
			<mul stat="mDef" value="#PMDef"/>
			<p_critical_damage value="#PMCritPower" type="PER"/>
			<p_skill_critical_damage value="#PMCritPower" type="PER"/>
			<p_magic_critical_dmg value="#PMCritPower" type="PER"/>
			<mul stat="pvpPhysDmgBonus" value="#PvpDmg"/>
			<mul stat="pvpMagicSkillDmgBonus" value="#PvpDmg"/>
			<mul stat="pvpPhysSkillDmgBonus" value="#PvpDmg"/>
			<mul stat="pvpPhysDefenceBonus" value="#PvpDef"/>
			<mul stat="pvpPhysSkillDefenceBonus" value="#PvpDef"/>
			<mul stat="pvpMagicSkillDefenceBonus" value="#PvpDef"/>
			<mul stat="pvePhysDmgBonus" value="#PveDmg"/>
			<mul stat="pveMagicSkillDmgBonus" value="#PveDmg"/>
			<mul stat="pvePhysSkillDmgBonus" value="#PveDmg"/>
			<mul stat="raid_boss_damage" value="#raid_boss_damage"/>
		</for>
	</skill>
	<skill id="36319" levels="4" name="Сказания Героя-древняя мудрость">
		<table name="#exp_rate_multiplier">0.1 0.2 0.3 0.4</table>
		<table name="#adena_rate_multiplier">0.05 0.1 0.15 0.2</table>
		<table name="#spirit_soul_shot_power">1.02 1.05 1.07 1.1</table>
		<set name="magicLevel" value="1"/>
		<set name="operate_type" value="P"/>
		<for>
			<add stat="exp_rate_multiplier" value="#exp_rate_multiplier"/>
			<add stat="adena_rate_multiplier" order="0x40" value="#adena_rate_multiplier"/>
			<mul stat="spiritshot_power" value="#spirit_soul_shot_power"/>
			<mul stat="soulshot_power" value="#spirit_soul_shot_power"/>
		</for>
	</skill>
</list>