<?xml version='1.0' encoding='utf-8'?>
<!DOCTYPE list SYSTEM "multisell.dtd">
<list>
	<config show_all="true" no_tax="true" keep_enchanted="false" />
	<!-- Талисман Безумия -->
	<item>
		<production id="104096" count="1"/>
		<ingredient count="111" id="57"/>
	</item>
	<item>
		<production id="104097" count="1"/>
		<ingredient count="111" id="57"/>
	</item>
	<item>
		<production id="104098" count="1"/>
		<ingredient count="111" id="57"/>
	</item>
	<item>
		<production id="104099" count="1"/>
		<ingredient count="111" id="57"/>
	</item>
	<item>
		<production id="104100" count="1"/>
		<ingredient count="111" id="57"/>
	</item>
	<item>
		<production id="104101" count="1"/>
		<ingredient count="111" id="57"/>
	</item>
	<item>
		<production id="104102" count="1"/>
		<ingredient count="111" id="57"/>
	</item>
	<item>
		<production id="104103" count="1"/>
		<ingredient count="111" id="57"/>
	</item>
	<item>
		<production id="104104" count="1"/>
		<ingredient count="111" id="57"/>
	</item>
	<item>
		<production id="104105" count="1"/>
		<ingredient count="111" id="57"/>
	</item>
</list>